{
  "user": "spotify",
  "id": "37i9dQZF1DWYiS8hkmdLyc",
  "name": "Classical World: Belgium & The Netherlands",
  "followers": 668,
  "tracks": [
    {
      "artists": [
        "César Franck",
        "Arthur Grumiaux",
        "György Sebök"
      ],
      "title": "Sonata for Violin and Piano in A: 4. Allegretto poco mosso",
      "album": "Fauré: Violin Sonata in E minor / Franck: Violin Sonata in A etc.",
      "id": "2yk67DhWWKga3CFkL171en",
      "trackNum": 11
    },
    {
      "artists": [
        "Johannes Ockeghem",
        "Capilla Flamenca"
      ],
      "title": "D'un autre amer: D'ung aultre amer",
      "album": "Oh Flanders Free: Music of the Flemish Renaissance",
      "id": "5JJpyIiI6apsFWFUG3SpmC",
      "trackNum": 9
    },
    {
      "artists": [
        "Eugène Ysaÿe",
        "Fenella Humphreys"
      ],
      "title": "Sonata in D Minor, Op. 27 No. 3 ‘Ballade’",
      "album": "Bach 2 the Future, Vol. 2",
      "id": "5LgswvLj116OWB7auuy6vm",
      "trackNum": 6,
      "best": "http://data.doremus.org/expression/1fc969f4-9387-33c6-9e0e-fba2170e6631",
      "best_matching_score": "0.93"
    },
    {
      "artists": [
        "Orlande de Lassus",
        "Collegium Vocale Gent",
        "Philippe Herreweghe"
      ],
      "title": "Qui timet Deum",
      "album": "Lassus: Cantiones sacrae sex vocum",
      "id": "72BHa9ZD4VGI72teH8FDvA",
      "trackNum": 4,
      "best": "http://data.doremus.org/expression/3e1fe6d1-9e38-348a-9c22-a951bfa53167",
      "best_matching_score": "1.00"
    },
    {
      "artists": [
        "Henri Vieuxtemps",
        "Hilary Hahn",
        "Deutsche Kammerphilharmonie Bremen",
        "Paavo Järvi"
      ],
      "title": "Violin Concerto No.4 In D Minor, Op.31: 1. Andante - Moderato",
      "album": "Mozart: Violin Concerto No.5 In A, K.219 / Vieuxtemps: Violin Concerto No.4 In D Minor, Op.31 (Bonus Track Version)",
      "id": "5XbsmbzGYvphfhFaaagAfv",
      "trackNum": 4
    },
    {
      "artists": [
        "Jan Pieterszoon Sweelinck",
        "Gustav Leonhardt"
      ],
      "title": "Toccata",
      "album": "Works For Harpsichord",
      "id": "3QcxP0cGmMYPDqEwHR1Tj5",
      "trackNum": 5,
      "best": "http://data.doremus.org/expression/4da8b0aa-f74d-386d-835e-b7d129ccc3c6",
      "best_matching_score": "0.86"
    },
    {
      "artists": [
        "Willem Pijper",
        "Netherlands Radio Symphony Orchestra",
        "Roland Brautigam",
        "Jac van Steen"
      ],
      "title": "Concert per piano e orchestra, K. 74 (1927)",
      "album": "Piano Concertos in the Netherlands",
      "id": "4DBm7pOmIyqRjbew2vtbA3",
      "trackNum": 4
    },
    {
      "artists": [
        "Unico Wilhelm van Wassenaer",
        "Ton Koopman",
        "Amsterdam Baroque Orchestra"
      ],
      "title": "Concerto Armonico No. 5 in F Minor",
      "album": "Van Wassenaer : 6 Concerti Armonici - APEX",
      "id": "24M7yH2kyOQMDYJM7Qo5yl",
      "trackNum": 11,
      "best": "http://data.doremus.org/expression/ff562918-11ee-3002-8b11-276c90072756",
      "best_matching_score": "0.80"
    },
    {
      "artists": [
        "Hendrik Andriessen",
        "Royal Concertgebouw Orchestra",
        "Bernard Haitink"
      ],
      "title": "Symphonische Etude (Quasi Adagio-Allegro con Spirito-Adagio-Allegro Vivace)",
      "album": "Bernard Haitink - The Philips Years",
      "id": "04lJiLpIbdvc07k1QXyIwN",
      "trackNum": 1
    },
    {
      "artists": [
        "Louis Andriessen",
        "Royal Concertgebouw Orchestra",
        "Mariss Jansons"
      ],
      "title": "Mysteriën: V. Over de verschillende bewegingen van de natuur en de genade",
      "album": "Mariss Jansons Live: The Radio Recordings 1990-2014",
      "id": "0i5jaF2O6Coq13fBFlYL01",
      "trackNum": 11
    },
    {
      "artists": [
        "Alphons Diepenbrock",
        "Hans Christoph Begemann",
        "Sinfonieorchester St. Gallen",
        "Otto Tausk"
      ],
      "title": "En sourdine",
      "album": "Diepenbrock: Orchestral Songs",
      "id": "6zucF0P4PT2TlYGcK2WTJD",
      "trackNum": 6
    },
    {
      "artists": [
        "Michel van der Aa",
        "Janine Jansen",
        "Royal Concertgebouw Orchestra",
        "Vladimir Jurowski"
      ],
      "title": "Violin Concerto: I. —",
      "album": "Horizon 6 (Live)",
      "id": "2c32t9hgCi9DLXNx2wmplH",
      "trackNum": 2
    },
    {
      "artists": [
        "Jacob van Eyck",
        "Walter van Hauwe"
      ],
      "title": "Pavane Lachrimae",
      "album": "Blockflutes 3",
      "id": "1Fu7nXhHrHXZNynkV75vlt",
      "trackNum": 5,
      "best": "http://data.doremus.org/expression/ff1c22a9-1e6f-3435-add5-70ec98d792cf",
      "best_matching_score": "0.88"
    },
    {
      "artists": [
        "Ton de Leeuw",
        "Philippe Graffin",
        "Jelger Blanken"
      ],
      "title": "Improvisation on the Dutch Christmas Carol \"Midden in de Winternacht\"",
      "album": "Pijper & Escher: Violin Sonatas etc.",
      "id": "2M84Wmfrgz6MM5QPmIFXF7",
      "trackNum": 16
    },
    {
      "artists": [
        "Guillaume Dufay",
        "Paul Van Nevel",
        "Huelgas Ensemble"
      ],
      "title": "O gemma, lux et speculum - Sacer pastor Barensium (Franco-Flemish Polyphony)",
      "album": "Dufay: O gemma lux",
      "id": "1tR0ZIfTSsk4EijLtaVAUJ",
      "trackNum": 3,
      "best": "http://data.doremus.org/expression/b5007059-b21e-3daa-9532-c0a2087c54e6",
      "best_matching_score": "1.00"
    },
    {
      "artists": [
        "Gilles Binchois",
        "Ensemble Gilles Binchois",
        "Dominique Vellard"
      ],
      "title": "Chansons: De plus en plus se renouvelle",
      "album": "Gilles Binchois - Chansons",
      "id": "1MGkyJLyG90n9JN06ERrwv",
      "trackNum": 8,
      "best": "http://data.doremus.org/expression/de63851c-430d-35de-ba61-50a99ff8728a",
      "best_matching_score": "0.78"
    },
    {
      "artists": [
        "Robin de Raaff",
        "The Hague Philharmonic",
        "Neeme Järvi"
      ],
      "title": "Entangled Tales, for Large Orchestra",
      "album": "Robin de Raaff: Entangled Tales",
      "id": "5zbrt0WXUriSoeYqQOTbPA",
      "trackNum": 6
    },
    {
      "artists": [
        "Antoine Busnois",
        "Fretwork"
      ],
      "title": "Le Serviteur, à 4",
      "album": "Ottaviano dei Petrucci: Harmonice Musices Odhecaton",
      "id": "0d84TVPP8H2RCoEdeeKiac",
      "trackNum": 18
    },
    {
      "artists": [
        "Heinrich Isaac",
        "Jordi Savall",
        "Sergi Casademunt",
        "Fahmi Alqhai"
      ],
      "title": "VII. Testamento de Isabel I y Muerte de Colon, 1506 (20 de mayo) Muere en Valladolid Cristóbal Colón: Fortuna desperata",
      "album": "Christophorus Columbus - Lost Paradises",
      "id": "3NLNMCNSz5oFHGmzUgpgQY",
      "trackNum": 20
    },
    {
      "artists": [
        "Jacob Clemens non Papa",
        "Stile Antico"
      ],
      "title": "Ego Flos Campi",
      "album": "Song of Songs",
      "id": "2NyeF5F1j2voBOSgUxSitj",
      "trackNum": 1
    },
    {
      "artists": [
        "Jacob Obrecht",
        "The Sixteen"
      ],
      "title": "Salve Regina",
      "album": "A Mother's Love - Music For Mary",
      "id": "4RzaInEebiZLH89SnodhWk",
      "trackNum": 8,
      "best": "http://data.doremus.org/expression/f21471a7-d0e0-3e98-a0c6-15cb59097706",
      "best_matching_score": "1.00"
    },
    {
      "artists": [
        "Philippe de Monte",
        "Gallicantus"
      ],
      "title": "Super flumina Babylonis",
      "album": "The Word Unspoken: Sacred Music by William Byrd and Philippe de Monte",
      "id": "5UzTMKIVL50Olb5hBCSc0t",
      "trackNum": 10,
      "best": "http://data.doremus.org/expression/0d76c762-3036-3c90-b145-5e637c64fd22",
      "best_matching_score": "1.00"
    },
    {
      "artists": [
        "Henri Dumont",
        "Greta de Reyghere",
        "Max van Egmont",
        "Ricercar Consort"
      ],
      "title": "Motets à deux voix, 1668: In lectulo meo, dialogus sponsae cum sponso coelesti",
      "album": "Du Mont: Motets à deux voix",
      "id": "57jVIII5o0RLthNM5FJLkS",
      "trackNum": 5
    },
    {
      "artists": [
        "André-Ernest-Modeste Grétry",
        "La Petite Bande",
        "Choeur de la Chapelle Royale de Paris",
        "Gustav Leonhardt"
      ],
      "title": "Le Jugement de Midas: Ouverture",
      "album": "Grétry: La Caravane du Caire",
      "id": "6YMTBP0kZdUsqK0Dc0bdXn",
      "trackNum": 8,
      "best": "http://data.doremus.org/expression/6d5a8f91-8ec8-313d-8040-91bab32219b2",
      "best_matching_score": "1.00"
    },
    {
      "artists": [
        "Francois-Joseph Gossec",
        "Kyung Wha Chung",
        "Phillip Moll"
      ],
      "title": "Gavotte",
      "album": "Con Amore",
      "id": "0LfoudDZusydpnmQ6RUywV",
      "trackNum": 13,
      "best": "http://data.doremus.org/expression/8a99b1c5-d752-3074-bb4d-062379e74e1d",
      "best_matching_score": "1.00"
    },
    {
      "artists": [
        "Wim Mertens"
      ],
      "title": "Multiple 12",
      "album": "Partes Extra Partes",
      "id": "0OpGVC3tH5pw2V0UfFG8kU",
      "trackNum": 7
    },
    {
      "artists": [
        "Guillaume Lekeu",
        "Tasmin Little",
        "Martin Roscoe"
      ],
      "title": "Violin Sonata in G Major: III. Tres anime",
      "album": "Fauré, Lekeu & Ravel: Violin Sonatas",
      "id": "4PufVRArEYMaYIx114QxPP",
      "trackNum": 3,
      "best": "http://data.doremus.org/expression/5df6fc76-7d1f-3702-8c10-a0e7fb64b80b",
      "best_matching_score": "0.75"
    },
    {
      "artists": [
        "Pierre de la Rue",
        "The Hilliard Ensemble"
      ],
      "title": "O salutaris Hostia",
      "album": "Franco-Flemish Masterworks",
      "id": "43MopskkE1zSuVIEFHl8Q1",
      "trackNum": 10,
      "best": "http://data.doremus.org/expression/7885519e-3328-353e-8811-83d49e657485",
      "best_matching_score": "1.00"
    },
    {
      "artists": [
        "Adrian Willaert",
        "Jordi Savall",
        "Hespèrion XXI"
      ],
      "title": "IV.1527 Saco de Roma: \"Vecchie Letrose\" (Villanesca Alla Napolitana)",
      "album": "Carlos V: Mille Regretz - La Canción Del Emperador",
      "id": "6L2GwsUlrwnB9BdNLSaHFy",
      "trackNum": 12
    },
    {
      "artists": [
        "Otto Ketting",
        "Royal Concertgebouw Orchestra",
        "Riccardo Chailly"
      ],
      "title": "Kom, over de zeeën",
      "album": "Otto Ketting: De Overtoch, De Aankomst, Het Oponthoud & Kom, Over De Zeeën",
      "id": "5TBuWk2WrQKDDUWku6WFVZ",
      "trackNum": 4
    }
  ],
  "n_matched": 13,
  "n_total": 30
}