{
  "id": "FM-401_20170213_00-02",
  "channel": "401",
  "records": [
    {
      "id": "3",
      "StepID": "3",
      "FatherStepID": "1",
      "AbsoluteScheduledDate": "2017-02-13",
      "ScheduledTime": "00:00:06:00",
      "ScheduledDuration": "00:06:08:00",
      "NumPhase": 2,
      "Inclusion": 0,
      "NumEventCond": 3,
      "TypEvent": "Primary Event",
      "StartMode": "Follow",
      "PressTitle": "5 novelettes op 15 : Alla spagnuola - Novelette op 15 n°1 / Dans le style espagnol",
      "BroadcastNature": "En différé",
      "TechnicalComment": "",
      "Intro1Duration": [
        "00:00:00:00",
        "00:00:00:00"
      ],
      "Intro1DurationMS": 0,
      "SoundId": "Titre de CD",
      "LongTitle": "5 novelettes op 15 : Alla spagnuola - Novelette op 15 n°1 / Dans le style espagnol",
      "Label": "OLYMPIA",
      "ReferenceLabel": "OCD 524",
      "ExternalID": "5015524405243-1-9",
      "AlbumTitle": "Glinka et Glazounov : Quatuor à cordes / Vol.4",
      "Rank": 9,
      "NumVolume": 1,
      "LibMusicalKind": "Musique de chambre",
      "Instru": false,
      "SupportType": "Fichier",
      "CDBarCode": "5015524405243",
      "Compositor": {
        "Highlight": true,
        "FullName": "Alexandre Glazounov",
        "Profession": "Compositeur/Compositrice"
      },
      "Interpreter": [
        {
          "FullName": "Quatuor Chostakovitch",
          "Profession": "Interprète",
          "InterventionNote": "Quatuor Chostakovitch"
        },
        {
          "FullName": "Andrei Shishlov",
          "Profession": "Interprète",
          "InterventionNote": "Andrei Shishlov : Violon",
          "mop": "Violon"
        },
        {
          "FullName": "Alexander Balashov",
          "Profession": "Interprète",
          "InterventionNote": "Alexander Balashov : Violon",
          "mop": "Violon"
        },
        {
          "FullName": "Alexander Galkovski",
          "Profession": "Interprète",
          "InterventionNote": "Alexander Galkovski : Alto (instrument)",
          "mop": "Alto (instrument)"
        },
        {
          "FullName": "Alexander Korchagin",
          "Profession": "Interprète",
          "InterventionNote": "Alexander Korchagin : Violoncelle",
          "mop": "Violoncelle"
        }
      ],
      "ScheduledDateTime": "2017-02-13T00:00:06+01:00",
      "composer": "http://data.doremus.org/artist/064a15a4-b08d-3300-9b18-91ca4e79671c"
    },
    {
      "id": "4",
      "StepID": "4",
      "FatherStepID": "1",
      "AbsoluteScheduledDate": "2017-02-13",
      "ScheduledTime": "00:06:14:00",
      "ScheduledDuration": "00:05:17:00",
      "NumPhase": 3,
      "Inclusion": 0,
      "NumEventCond": 4,
      "TypEvent": "Primary Event",
      "StartMode": "Follow",
      "PressTitle": "Alborada : Andantino- pour 2 orgues obliges",
      "BroadcastNature": "En différé",
      "TechnicalComment": "",
      "Intro1Duration": [
        "00:00:00:00",
        "00:00:00:00"
      ],
      "Intro1DurationMS": 0,
      "SoundId": "Titre de CD",
      "LongTitle": "Alborada : Andantino- pour 2 orgues obliges",
      "Label": "CALLIOPE",
      "ReferenceLabel": "CAL 9749",
      "ExternalID": "0794881860029-1-2",
      "AlbumTitle": "Alborada / Oeuvres pour orgue et duo de guitares",
      "Rank": 2,
      "NumVolume": 1,
      "PublicationDate": "2005-01-01",
      "LibMusicalKind": "Musique de chambre",
      "Instru": false,
      "SupportType": "Fichier",
      "CDBarCode": "0794881860029",
      "Compositor": {
        "Highlight": true,
        "FullName": "Antonio Soler",
        "Profession": "Compositeur/Compositrice"
      },
      "Interpreter": [
        {
          "FullName": "Trio Alborada",
          "Profession": "Interprète",
          "InterventionNote": "Trio Alborada"
        },
        {
          "FullName": "Andre Isoir",
          "Profession": "Interprète",
          "InterventionNote": "Andre Isoir : Orgue positif",
          "mop": "Orgue positif"
        },
        {
          "FullName": "Patrick Guillem",
          "Profession": "Interprète",
          "InterventionNote": "Patrick Guillem : Guitare",
          "mop": "Guitare"
        },
        {
          "FullName": "Didier Magne",
          "Profession": "Interprète",
          "InterventionNote": "Didier Magne : Guitare",
          "mop": "Guitare"
        }
      ],
      "ScheduledDateTime": "2017-02-13T00:06:14+01:00",
      "composer": "http://data.doremus.org/artist/4b760714-97cf-33a2-ae88-27c5c64cb606"
    },
    {
      "id": "5",
      "StepID": "5",
      "FatherStepID": "1",
      "AbsoluteScheduledDate": "2017-02-13",
      "ScheduledTime": "00:11:31:00",
      "ScheduledDuration": "00:04:54:00",
      "NumPhase": 4,
      "Inclusion": 0,
      "NumEventCond": 5,
      "TypEvent": "Primary Event",
      "StartMode": "Follow",
      "PressTitle": "Danse espagnole n°2 : orientale - arrangement pour 2 guitares",
      "BroadcastNature": "En différé",
      "TechnicalComment": "",
      "Intro1Duration": [
        "00:00:00:00",
        "00:00:00:00"
      ],
      "Intro1DurationMS": 0,
      "SoundId": "Titre de CD",
      "LongTitle": "Danse espagnole n°2 : orientale - arrangement pour 2 guitares",
      "Label": "CALLIOPE",
      "ReferenceLabel": "CAL 9749",
      "ExternalID": "0794881860029-1-8",
      "AlbumTitle": "Alborada / Oeuvres pour orgue et duo de guitares",
      "Rank": 8,
      "NumVolume": 1,
      "PublicationDate": "2005-01-01",
      "LibMusicalKind": "Musique de chambre",
      "Instru": false,
      "SupportType": "Fichier",
      "CDBarCode": "0794881860029",
      "Compositor": {
        "Highlight": true,
        "FullName": "Enrique Granados",
        "Profession": "Compositeur/Compositrice"
      },
      "Interpreter": [
        {
          "FullName": "Trio Alborada",
          "Profession": "Interprète",
          "InterventionNote": "Trio Alborada"
        },
        {
          "FullName": "Patrick Guillem",
          "Profession": "Interprète",
          "InterventionNote": "Patrick Guillem : Guitare",
          "mop": "Guitare"
        },
        {
          "FullName": "Didier Magne",
          "Profession": "Interprète",
          "InterventionNote": "Didier Magne : Guitare",
          "mop": "Guitare"
        }
      ],
      "ScheduledDateTime": "2017-02-13T00:11:31+01:00",
      "composer": "http://data.doremus.org/artist/f482df1a-9990-3708-8950-674bad8c4289",
      "best": "http://data.doremus.org/expression/69de39d0-0bd3-32d9-981a-712fb5d6f26d",
      "best_matching_score": "0.90"
    },
    {
      "id": "6",
      "StepID": "6",
      "FatherStepID": "1",
      "AbsoluteScheduledDate": "2017-02-13",
      "ScheduledTime": "00:16:25:00",
      "ScheduledDuration": "00:07:34:00",
      "NumPhase": 5,
      "Inclusion": 0,
      "NumEventCond": 6,
      "TypEvent": "Primary Event",
      "StartMode": "Follow",
      "PressTitle": "Miroirs : Alborada del gracioso - pour orchestre",
      "BroadcastNature": "En différé",
      "TechnicalComment": "",
      "Intro1Duration": [
        "00:00:00:00",
        "00:00:00:00"
      ],
      "Intro1DurationMS": 0,
      "SoundId": "Titre de CD",
      "LongTitle": "Miroirs : Alborada del gracioso - pour orchestre",
      "Label": "EMI",
      "ReferenceLabel": "7640562",
      "ExternalID": "0077776405629-1-14",
      "AlbumTitle": "Debussy",
      "Rank": 14,
      "NumVolume": 1,
      "LibMusicalKind": "Musique symphonique",
      "Instru": false,
      "SupportType": "Fichier",
      "CDBarCode": "0077776405629",
      "Compositor": {
        "Highlight": true,
        "FullName": "Maurice Ravel",
        "Profession": "Compositeur/Compositrice"
      },
      "Orchestra": {
        "EntityName": "Royal Philharmonic Orchestra De Londres",
        "EntityType": "Orchestre"
      },
      "OrchestraLeader": {
        "FullName": "Andre Previn",
        "Profession": "Chef d'orchestre"
      },
      "ScheduledDateTime": "2017-02-13T00:16:25+01:00",
      "composer": "http://data.doremus.org/artist/1b1205f9-b99a-3bb8-ba77-256689af2e00",
      "best": "http://data.doremus.org/expression/ecf574cf-4363-3743-a6af-3ef3f26f7334",
      "best_matching_score": "1.00"
    },
    {
      "id": "8",
      "StepID": "8",
      "FatherStepID": "1",
      "AbsoluteScheduledDate": "2017-02-13",
      "ScheduledTime": "00:24:10:00",
      "ScheduledDuration": "00:04:40:00",
      "NumPhase": 7,
      "Inclusion": 0,
      "NumEventCond": 8,
      "TypEvent": "Primary Event",
      "StartMode": "Follow",
      "PressTitle": "Capriccio espagnol op 34 : Variazioni - pour orchestre",
      "BroadcastNature": "En différé",
      "TechnicalComment": "",
      "Intro1Duration": [
        "00:00:00:00",
        "00:00:00:00"
      ],
      "Intro1DurationMS": 0,
      "SoundId": "Titre de CD",
      "LongTitle": "Capriccio espagnol op 34 : Variazioni - pour orchestre",
      "Label": "MERCURY",
      "ReferenceLabel": "434308-2",
      "ExternalID": "0042243430824-1-2",
      "AlbumTitle": "Antal Dorati dirige Rimsky-Korsakov et Borodine",
      "Rank": 2,
      "NumVolume": 1,
      "PublicationDate": "1992-01-01",
      "LibMusicalKind": "Musique symphonique",
      "Instru": false,
      "SupportType": "Fichier",
      "CDBarCode": "0042243430824",
      "Compositor": {
        "Highlight": true,
        "FullName": "Nicolas Rimski-Korsakov",
        "Profession": "Compositeur/Compositrice"
      },
      "Orchestra": {
        "EntityName": "Orchestre Symphonique De Londres",
        "EntityType": "Orchestre"
      },
      "OrchestraLeader": {
        "FullName": "Antal Dorati",
        "Profession": "Chef d'orchestre"
      },
      "ScheduledDateTime": "2017-02-13T00:24:10+01:00"
    },
    {
      "id": "9",
      "StepID": "9",
      "FatherStepID": "1",
      "AbsoluteScheduledDate": "2017-02-13",
      "ScheduledTime": "00:28:50:00",
      "ScheduledDuration": "00:03:37:00",
      "NumPhase": 8,
      "Inclusion": 0,
      "NumEventCond": 9,
      "TypEvent": "Primary Event",
      "StartMode": "Follow",
      "PressTitle": "Amorosa - pour orchestre",
      "BroadcastNature": "En différé",
      "TechnicalComment": "",
      "Intro1Duration": [
        "00:00:00:00",
        "00:00:00:00"
      ],
      "Intro1DurationMS": 0,
      "SoundId": "Titre de CD",
      "LongTitle": "Amorosa - pour orchestre",
      "Label": "SONY",
      "ReferenceLabel": "88725404892",
      "ExternalID": "0887254048923-1-2",
      "AlbumTitle": "Ataulfo Argenta dirige le meilleur de la musique espagnole",
      "Rank": 2,
      "NumVolume": 1,
      "PublicationDate": "2012-01-01",
      "LibMusicalKind": "Musique symphonique",
      "Instru": false,
      "SupportType": "Fichier",
      "CDBarCode": "0887254048923",
      "Compositor": {
        "Highlight": true,
        "FullName": "Jesus Guridi",
        "Profession": "Compositeur/Compositrice"
      },
      "Orchestra": {
        "EntityName": "Orchestre National D'Espagne",
        "EntityType": "Orchestre"
      },
      "OrchestraLeader": {
        "FullName": "Ataulfo Argenta",
        "Profession": "Chef d'orchestre"
      },
      "ScheduledDateTime": "2017-02-13T00:28:50+01:00",
      "composer": "http://data.doremus.org/artist/7e2355d2-fb16-3ae2-8245-9889f5ea2a9e"
    },
    {
      "id": "10",
      "StepID": "10",
      "FatherStepID": "1",
      "AbsoluteScheduledDate": "2017-02-13",
      "ScheduledTime": "00:32:27:00",
      "ScheduledDuration": "00:07:28:00",
      "NumPhase": 9,
      "Inclusion": 0,
      "NumEventCond": 10,
      "TypEvent": "Primary Event",
      "StartMode": "Follow",
      "PressTitle": "Les Nations 2ème ordre : L'Espagnole : Sonade - La visionnaire",
      "BroadcastNature": "En différé",
      "TechnicalComment": "",
      "Intro1Duration": [
        "00:00:00:00",
        "00:00:00:00"
      ],
      "Intro1DurationMS": 0,
      "SoundId": "Titre de CD",
      "LongTitle": "Les Nations 2ème ordre : L'Espagnole : Sonade - La visionnaire",
      "Label": "ACCENT",
      "ReferenceLabel": "ACC 9285/86 D",
      "ExternalID": "5413633928569-1-10",
      "AlbumTitle": "François Couperin : Les Nations (intégrale)",
      "Rank": 10,
      "NumVolume": 1,
      "LibMusicalKind": "Musique de chambre",
      "Instru": false,
      "SupportType": "Fichier",
      "CDBarCode": "5413633928569",
      "Compositor": {
        "Highlight": true,
        "FullName": "Francois Couperin",
        "Profession": "Compositeur/Compositrice"
      },
      "Interpreter": [
        {
          "FullName": "Ensemble Kuijken",
          "Profession": "Interprète",
          "InterventionNote": "Ensemble Kuijken"
        },
        {
          "FullName": "Barthold Kuijken",
          "Profession": "Interprète",
          "InterventionNote": "Barthold Kuijken : Flûte traversière baroque",
          "mop": "Flûte traversière baroque"
        },
        {
          "FullName": "Marc Hantai",
          "Profession": "Interprète",
          "InterventionNote": "Marc Hantai : Flûte traversière baroque",
          "mop": "Flûte traversière baroque"
        },
        {
          "FullName": "Sigiswald Kuijken",
          "Profession": "Interprète",
          "InterventionNote": "Sigiswald Kuijken : Violon",
          "mop": "Violon"
        },
        {
          "FullName": "Francois Fernandez",
          "Profession": "Interprète",
          "InterventionNote": "Francois Fernandez : Violon",
          "mop": "Violon"
        },
        {
          "FullName": "Wieland Kuijken",
          "Profession": "Interprète",
          "InterventionNote": "Wieland Kuijken : Basse de viole",
          "mop": "Basse de viole"
        },
        {
          "FullName": "Robert Kohnen",
          "Profession": "Interprète",
          "InterventionNote": "Robert Kohnen : Clavecin",
          "mop": "Clavecin"
        }
      ],
      "ScheduledDateTime": "2017-02-13T00:32:27+01:00",
      "composer": "http://data.doremus.org/artist/14970460-189f-3593-a550-7bceb778072e"
    },
    {
      "id": "11",
      "StepID": "11",
      "FatherStepID": "1",
      "AbsoluteScheduledDate": "2017-02-13",
      "ScheduledTime": "00:39:55:00",
      "ScheduledDuration": "00:02:38:00",
      "NumPhase": 10,
      "Inclusion": 0,
      "NumEventCond": 11,
      "TypEvent": "Primary Event",
      "StartMode": "Follow",
      "PressTitle": "Rapsodie espagnole S 254 : Jota aragonese",
      "BroadcastNature": "En différé",
      "TechnicalComment": "",
      "Intro1Duration": [
        "00:00:00:00",
        "00:00:00:00"
      ],
      "Intro1DurationMS": 0,
      "SoundId": "Titre de CD",
      "LongTitle": "Rapsodie espagnole S 254 : Jota aragonese",
      "Label": "BRILLIANT CLASSICS",
      "ReferenceLabel": "95300/22",
      "ExternalID": "RF00000054337-1-8",
      "AlbumTitle": "Concertos romantiques pour piano CD 22",
      "Rank": 8,
      "NumVolume": 1,
      "LibMusicalKind": "Musique symphonique",
      "Instru": false,
      "SupportType": "Fichier",
      "CDBarCode": "RF00000054337",
      "Compositor": {
        "Highlight": true,
        "FullName": "Franz Liszt",
        "Profession": "Compositeur/Compositrice"
      },
      "Author": {
        "FullName": "Ferruccio Bbusoni",
        "Profession": "Bruiteur",
        "InterventionNote": "Ferruccio Bbusoni : Arrangeur"
      },
      "Interpreter": {
        "FullName": "Felicja Blumenthal",
        "Profession": "Interprète",
        "InterventionNote": "Felicja Blumenthal : Piano",
        "mop": "Piano"
      },
      "Orchestra": {
        "EntityName": "Orchestre Symphonique De Prague",
        "EntityType": "Orchestre"
      },
      "OrchestraLeader": {
        "FullName": "Helmuth Froschauer",
        "Profession": "Chef d'orchestre"
      },
      "ScheduledDateTime": "2017-02-13T00:39:55+01:00",
      "composer": "http://data.doremus.org/artist/aabcd2ee-ac9b-30f2-8096-e9de8b3c7a81"
    },
    {
      "id": "12",
      "StepID": "12",
      "FatherStepID": "1",
      "AbsoluteScheduledDate": "2017-02-13",
      "ScheduledTime": "00:42:33:00",
      "ScheduledDuration": "00:03:23:00",
      "NumPhase": 11,
      "Inclusion": 0,
      "NumEventCond": 12,
      "TypEvent": "Primary Event",
      "StartMode": "Follow",
      "PressTitle": "Les filles de cadix pour soprano et piano",
      "BroadcastNature": "En différé",
      "TechnicalComment": "",
      "Intro1Duration": [
        "00:00:00:00",
        "00:00:00:00"
      ],
      "Intro1DurationMS": 0,
      "SoundId": "Titre de CD",
      "LongTitle": "Les filles de cadix pour soprano et piano",
      "Label": "DECCA",
      "ReferenceLabel": "458360-2",
      "ExternalID": "0028945836027-1-8",
      "AlbumTitle": "Angela Gheorghiu : Souvenirs",
      "Rank": 8,
      "NumVolume": 1,
      "PublicationDate": "1998-01-01",
      "LibMusicalKind": "Musique chorale et vocale",
      "Instru": false,
      "SupportType": "Fichier",
      "CDBarCode": "0028945836027",
      "Compositor": {
        "Highlight": true,
        "FullName": "Leo Delibes",
        "Profession": "Compositeur/Compositrice"
      },
      "Interpreter": [
        {
          "FullName": "Angela Gheorghiu",
          "Profession": "Interprète",
          "InterventionNote": "Angela Gheorghiu : Soprano",
          "mop": "Soprano"
        },
        {
          "FullName": "Malcom Martineau",
          "Profession": "Interprète",
          "InterventionNote": "Malcom Martineau : Piano",
          "mop": "Piano"
        }
      ],
      "ScheduledDateTime": "2017-02-13T00:42:33+01:00",
      "composer": "http://data.doremus.org/artist/5e166265-3cbf-3b0c-b7f5-a09b82e3a279"
    },
    {
      "id": "13",
      "StepID": "13",
      "FatherStepID": "1",
      "AbsoluteScheduledDate": "2017-02-13",
      "ScheduledTime": "00:45:56:00",
      "ScheduledDuration": "00:01:38:00",
      "NumPhase": 12,
      "Inclusion": 0,
      "NumEventCond": 13,
      "TypEvent": "Primary Event",
      "StartMode": "Follow",
      "PressTitle": "Coppélia : Boléro (Acte II Sc 16)",
      "BroadcastNature": "En différé",
      "TechnicalComment": "",
      "Intro1Duration": [
        "00:00:00:00",
        "00:00:00:00"
      ],
      "Intro1DurationMS": 0,
      "SoundId": "Titre de CD",
      "LongTitle": "Coppélia : Boléro (Acte II Sc 16)",
      "Label": "DECCA",
      "ReferenceLabel": "4807918",
      "ExternalID": "RF00000053295-1-19",
      "AlbumTitle": "Ernest Ansermet : French music CD 20 & 21",
      "Rank": 19,
      "NumVolume": 1,
      "PublicationDate": "2013-01-01",
      "LibMusicalKind": "Musique symphonique",
      "Instru": false,
      "SupportType": "Fichier",
      "CDBarCode": "RF00000053295",
      "Compositor": {
        "Highlight": true,
        "FullName": "Leo Delibes",
        "Profession": "Compositeur/Compositrice"
      },
      "Orchestra": {
        "EntityName": "Orchestre De La Suisse Romande",
        "EntityType": "Orchestre"
      },
      "OrchestraLeader": {
        "FullName": "Ernest Ansermet",
        "Profession": "Chef d'orchestre"
      },
      "ScheduledDateTime": "2017-02-13T00:45:56+01:00",
      "composer": "http://data.doremus.org/artist/5e166265-3cbf-3b0c-b7f5-a09b82e3a279",
      "best": "http://data.doremus.org/expression/1d75b063-2e8a-3110-9010-33cde28de98a",
      "best_matching_score": "1.00"
    },
    {
      "id": "15",
      "StepID": "15",
      "FatherStepID": "1",
      "AbsoluteScheduledDate": "2017-02-13",
      "ScheduledTime": "00:47:38:00",
      "ScheduledDuration": "00:03:26:00",
      "NumPhase": 14,
      "Inclusion": 0,
      "NumEventCond": 15,
      "TypEvent": "Primary Event",
      "StartMode": "Follow",
      "PressTitle": "5 novelettes op 15 : Orientale - Novelette op 15 n°2 / Dans le style oriental",
      "BroadcastNature": "En différé",
      "TechnicalComment": "",
      "Intro1Duration": [
        "00:00:00:00",
        "00:00:00:00"
      ],
      "Intro1DurationMS": 0,
      "SoundId": "Titre de CD",
      "LongTitle": "5 novelettes op 15 : Orientale - Novelette op 15 n°2 / Dans le style oriental",
      "Label": "OLYMPIA",
      "ReferenceLabel": "OCD 524",
      "ExternalID": "5015524405243-1-10",
      "AlbumTitle": "Glinka et Glazounov : Quatuor à cordes / Vol.4",
      "Rank": 10,
      "NumVolume": 1,
      "LibMusicalKind": "Musique de chambre",
      "Instru": false,
      "SupportType": "Fichier",
      "CDBarCode": "5015524405243",
      "Compositor": {
        "Highlight": true,
        "FullName": "Alexandre Glazounov",
        "Profession": "Compositeur/Compositrice"
      },
      "Interpreter": [
        {
          "FullName": "Quatuor Chostakovitch",
          "Profession": "Interprète",
          "InterventionNote": "Quatuor Chostakovitch"
        },
        {
          "FullName": "Andrei Shishlov",
          "Profession": "Interprète",
          "InterventionNote": "Andrei Shishlov : Violon",
          "mop": "Violon"
        },
        {
          "FullName": "Alexander Balashov",
          "Profession": "Interprète",
          "InterventionNote": "Alexander Balashov : Violon",
          "mop": "Violon"
        },
        {
          "FullName": "Alexander Galkovski",
          "Profession": "Interprète",
          "InterventionNote": "Alexander Galkovski : Alto (instrument)",
          "mop": "Alto (instrument)"
        },
        {
          "FullName": "Alexander Korchagin",
          "Profession": "Interprète",
          "InterventionNote": "Alexander Korchagin : Violoncelle",
          "mop": "Violoncelle"
        }
      ],
      "ScheduledDateTime": "2017-02-13T00:47:38+01:00",
      "composer": "http://data.doremus.org/artist/064a15a4-b08d-3300-9b18-91ca4e79671c"
    },
    {
      "id": "16",
      "StepID": "16",
      "FatherStepID": "1",
      "AbsoluteScheduledDate": "2017-02-13",
      "ScheduledTime": "00:51:04:00",
      "ScheduledDuration": "00:01:30:00",
      "NumPhase": 15,
      "Inclusion": 0,
      "NumEventCond": 16,
      "TypEvent": "Primary Event",
      "StartMode": "Follow",
      "PressTitle": "Les orientales : Nuits d'Egypte op 50 : Danse égyptienne - prélude à L'oiseau de feu pour orchestre",
      "BroadcastNature": "En différé",
      "TechnicalComment": "",
      "Intro1Duration": [
        "00:00:00:00",
        "00:00:00:00"
      ],
      "Intro1DurationMS": 0,
      "SoundId": "Titre de CD",
      "LongTitle": "Les orientales : Nuits d'Egypte op 50 : Danse égyptienne - prélude à L'oiseau de feu pour orchestre",
      "Label": "MUSICALES ACTES SUD",
      "ReferenceLabel": "ASM 06",
      "ExternalID": "3149028001822-1-5",
      "AlbumTitle": "Les Siècles interprètent L'oiseau de feu de Stravinsky et les Orientales",
      "Rank": 5,
      "NumVolume": 1,
      "PublicationDate": "2011-01-01",
      "LibMusicalKind": "Musique symphonique",
      "Instru": false,
      "SupportType": "Fichier",
      "CDBarCode": "3149028001822",
      "Compositor": {
        "Highlight": true,
        "FullName": "Anton Stepanovitch Arenski",
        "Profession": "Compositeur/Compositrice"
      },
      "Orchestra": {
        "EntityName": "Orchestre Les Siecles",
        "EntityType": "Orchestre"
      },
      "OrchestraLeader": {
        "FullName": "Francois Xavier Roth",
        "Profession": "Chef d'orchestre"
      },
      "ScheduledDateTime": "2017-02-13T00:51:04+01:00",
      "composer": "http://data.doremus.org/artist/a149a195-b1f9-388e-96ae-d7c6866f9fc2"
    },
    {
      "id": "17",
      "StepID": "17",
      "FatherStepID": "1",
      "AbsoluteScheduledDate": "2017-02-13",
      "ScheduledTime": "00:52:34:00",
      "ScheduledDuration": "00:01:16:00",
      "NumPhase": 16,
      "Inclusion": 0,
      "NumEventCond": 17,
      "TypEvent": "Primary Event",
      "StartMode": "Follow",
      "PressTitle": "Les orientales : Nuits d'Egypte op 50 : La charmeuse de serpent - prélude à L'oiseau de feu pour orchestre",
      "BroadcastNature": "En différé",
      "TechnicalComment": "",
      "Intro1Duration": [
        "00:00:00:00",
        "00:00:00:00"
      ],
      "Intro1DurationMS": 0,
      "SoundId": "Titre de CD",
      "LongTitle": "Les orientales : Nuits d'Egypte op 50 : La charmeuse de serpent - prélude à L'oiseau de feu pour orchestre",
      "Label": "MUSICALES ACTES SUD",
      "ReferenceLabel": "ASM 06",
      "ExternalID": "3149028001822-1-6",
      "AlbumTitle": "Les Siècles interprètent L'oiseau de feu de Stravinsky et les Orientales",
      "Rank": 6,
      "NumVolume": 1,
      "PublicationDate": "2011-01-01",
      "LibMusicalKind": "Musique symphonique",
      "Instru": false,
      "SupportType": "Fichier",
      "CDBarCode": "3149028001822",
      "Compositor": {
        "Highlight": true,
        "FullName": "Anton Stepanovitch Arenski",
        "Profession": "Compositeur/Compositrice"
      },
      "Orchestra": {
        "EntityName": "Orchestre Les Siecles",
        "EntityType": "Orchestre"
      },
      "OrchestraLeader": {
        "FullName": "Francois Xavier Roth",
        "Profession": "Chef d'orchestre"
      },
      "ScheduledDateTime": "2017-02-13T00:52:34+01:00",
      "composer": "http://data.doremus.org/artist/a149a195-b1f9-388e-96ae-d7c6866f9fc2"
    },
    {
      "id": "18",
      "StepID": "18",
      "FatherStepID": "1",
      "AbsoluteScheduledDate": "2017-02-13",
      "ScheduledTime": "00:53:50:00",
      "ScheduledDuration": "00:02:16:00",
      "NumPhase": 17,
      "Inclusion": 0,
      "NumEventCond": 18,
      "TypEvent": "Primary Event",
      "StartMode": "Follow",
      "PressTitle": "Les orientales : Nuits d'Egypte op 50 : Danse des Ghazies - prélude à L'oiseau de feu pour orchestre",
      "BroadcastNature": "En différé",
      "TechnicalComment": "",
      "Intro1Duration": [
        "00:00:00:00",
        "00:00:00:00"
      ],
      "Intro1DurationMS": 0,
      "SoundId": "Titre de CD",
      "LongTitle": "Les orientales : Nuits d'Egypte op 50 : Danse des Ghazies - prélude à L'oiseau de feu pour orchestre",
      "Label": "MUSICALES ACTES SUD",
      "ReferenceLabel": "ASM 06",
      "ExternalID": "3149028001822-1-7",
      "AlbumTitle": "Les Siècles interprètent L'oiseau de feu de Stravinsky et les Orientales",
      "Rank": 7,
      "NumVolume": 1,
      "PublicationDate": "2011-01-01",
      "LibMusicalKind": "Musique symphonique",
      "Instru": false,
      "SupportType": "Fichier",
      "CDBarCode": "3149028001822",
      "Compositor": {
        "Highlight": true,
        "FullName": "Anton Stepanovitch Arenski",
        "Profession": "Compositeur/Compositrice"
      },
      "Orchestra": {
        "EntityName": "Orchestre Les Siecles",
        "EntityType": "Orchestre"
      },
      "OrchestraLeader": {
        "FullName": "Francois Xavier Roth",
        "Profession": "Chef d'orchestre"
      },
      "ScheduledDateTime": "2017-02-13T00:53:50+01:00",
      "composer": "http://data.doremus.org/artist/a149a195-b1f9-388e-96ae-d7c6866f9fc2"
    },
    {
      "id": "19",
      "StepID": "19",
      "FatherStepID": "1",
      "AbsoluteScheduledDate": "2017-02-13",
      "ScheduledTime": "00:56:06:00",
      "ScheduledDuration": "00:05:54:00",
      "NumPhase": 18,
      "Inclusion": 0,
      "NumEventCond": 19,
      "TypEvent": "Primary Event",
      "StartMode": "Follow",
      "PressTitle": "Sheherazade : Chant et danse orientale",
      "BroadcastNature": "En différé",
      "TechnicalComment": "",
      "Intro1Duration": [
        "00:00:00:00",
        "00:00:00:00"
      ],
      "Intro1DurationMS": 0,
      "SoundId": "Titre de CD",
      "LongTitle": "Sheherazade : Chant et danse orientale",
      "Label": "DECCA",
      "ReferenceLabel": "425200-2",
      "ExternalID": "0028942520028-1-13",
      "AlbumTitle": "Orient express",
      "Rank": 13,
      "NumVolume": 1,
      "PublicationDate": "1989-01-01",
      "LibMusicalKind": "Musique de chambre",
      "Instru": false,
      "SupportType": "Fichier",
      "CDBarCode": "0028942520028",
      "Compositor": {
        "Highlight": true,
        "FullName": "Nicolas Rimski-Korsakov",
        "Profession": "Compositeur/Compositrice"
      },
      "Interpreter": {
        "FullName": "I Salonisti",
        "Profession": "Interprète",
        "InterventionNote": "I Salonisti"
      },
      "ScheduledDateTime": "2017-02-13T00:56:06+01:00"
    },
    {
      "id": "20",
      "StepID": "20",
      "FatherStepID": "1",
      "AbsoluteScheduledDate": "2017-02-13",
      "ScheduledTime": "01:02:00:00",
      "ScheduledDuration": "00:03:39:00",
      "NumPhase": 19,
      "Inclusion": 0,
      "NumEventCond": 20,
      "TypEvent": "Primary Event",
      "StartMode": "Follow",
      "PressTitle": "Villancico Virgen bendita",
      "BroadcastNature": "En différé",
      "TechnicalComment": "",
      "Intro1Duration": [
        "00:00:00:00",
        "00:00:00:00"
      ],
      "Intro1DurationMS": 0,
      "SoundId": "Titre de CD",
      "LongTitle": "Villancico Virgen bendita",
      "Label": "ALIA VOX",
      "ReferenceLabel": "AVSA 9856",
      "ExternalID": "7619986398563-1-2",
      "AlbumTitle": "Saint François Xavier : La route de l'Orient /Francisco Javier : La ruta de Oriente",
      "Rank": 2,
      "NumVolume": 1,
      "PublicationDate": "2007-01-01",
      "LibMusicalKind": "Musique ancienne",
      "Instru": false,
      "SupportType": "Fichier",
      "CDBarCode": "7619986398563",
      "Compositor": {
        "Highlight": true,
        "FullName": "Pedro De Escobar",
        "Profession": "Compositeur/Compositrice"
      },
      "Interpreter": [
        {
          "FullName": "Montserrat Figueras",
          "Profession": "Interprète",
          "InterventionNote": "Montserrat Figueras : Soprano",
          "mop": "Soprano"
        },
        {
          "FullName": "Hesperion Xxi",
          "Profession": "Interprète",
          "InterventionNote": "Hesperion Xxi"
        },
        {
          "FullName": "Capella Reial De Catalogne",
          "Profession": "Interprète",
          "InterventionNote": "Capella Reial De Catalogne"
        },
        {
          "FullName": "Arianna Savall",
          "Profession": "Interprète",
          "InterventionNote": "Arianna Savall : Soprano",
          "mop": "Soprano"
        },
        {
          "FullName": "Pascal Bertin",
          "Profession": "Interprète",
          "InterventionNote": "Pascal Bertin : Haute-contre",
          "mop": "Haute-contre"
        },
        {
          "FullName": "David Sagastume",
          "Profession": "Interprète",
          "InterventionNote": "David Sagastume : Haute-contre",
          "mop": "Haute-contre"
        },
        {
          "FullName": "Lambert Climent",
          "Profession": "Interprète",
          "InterventionNote": "Lambert Climent : Ténor",
          "mop": "Ténor"
        },
        {
          "FullName": "Divers",
          "Profession": "Interprète",
          "InterventionNote": "Divers"
        }
      ],
      "OrchestraLeader": {
        "FullName": "Jordi Savall",
        "Profession": "Chef d'orchestre"
      },
      "ScheduledDateTime": "2017-02-13T01:02:00+01:00",
      "composer": "http://data.doremus.org/artist/934a1a23-f3a1-3a6f-b401-2495f8fd15f6"
    },
    {
      "id": "21",
      "StepID": "21",
      "FatherStepID": "1",
      "AbsoluteScheduledDate": "2017-02-13",
      "ScheduledTime": "01:05:39:00",
      "ScheduledDuration": "00:03:58:00",
      "NumPhase": 20,
      "Inclusion": 0,
      "NumEventCond": 21,
      "TypEvent": "Primary Event",
      "StartMode": "Follow",
      "PressTitle": "Villancico Adoramoste Señor",
      "BroadcastNature": "En différé",
      "TechnicalComment": "",
      "Intro1Duration": [
        "00:00:00:00",
        "00:00:00:00"
      ],
      "Intro1DurationMS": 0,
      "SoundId": "Titre de CD",
      "LongTitle": "Villancico Adoramoste Señor",
      "Label": "ALIA VOX",
      "ReferenceLabel": "AVSA 9856",
      "ExternalID": "7619986398563-2-14",
      "AlbumTitle": "Saint François Xavier : La route de l'Orient /Francisco Javier : La ruta de Oriente",
      "Rank": 14,
      "NumVolume": 2,
      "LibMusicalKind": "Musique ancienne",
      "Instru": false,
      "SupportType": "Fichier",
      "CDBarCode": "7619986398563",
      "Compositor": {
        "Highlight": true,
        "FullName": "Francisco De La Torre",
        "Profession": "Compositeur/Compositrice"
      },
      "Interpreter": [
        {
          "FullName": "Montserrat Figueras",
          "Profession": "Interprète",
          "InterventionNote": "Montserrat Figueras : Soprano",
          "mop": "Soprano"
        },
        {
          "FullName": "Hesperion Xxi",
          "Profession": "Interprète",
          "InterventionNote": "Hesperion Xxi"
        },
        {
          "FullName": "Capella Reial De Catalogne",
          "Profession": "Interprète",
          "InterventionNote": "Capella Reial De Catalogne"
        },
        {
          "FullName": "Arianna Savall",
          "Profession": "Interprète",
          "InterventionNote": "Arianna Savall : Soprano",
          "mop": "Soprano"
        },
        {
          "FullName": "Pascal Bertin",
          "Profession": "Interprète",
          "InterventionNote": "Pascal Bertin : Haute-contre",
          "mop": "Haute-contre"
        },
        {
          "FullName": "David Sagastume",
          "Profession": "Interprète",
          "InterventionNote": "David Sagastume : Haute-contre",
          "mop": "Haute-contre"
        },
        {
          "FullName": "Divers",
          "Profession": "Interprète",
          "InterventionNote": "Divers"
        }
      ],
      "OrchestraLeader": {
        "FullName": "Jordi Savall",
        "Profession": "Chef d'orchestre"
      },
      "ScheduledDateTime": "2017-02-13T01:05:39+01:00",
      "composer": "http://data.doremus.org/artist/5f2d7a6e-4540-3830-8e75-f3e3b7fb8ba2"
    },
    {
      "id": "22",
      "StepID": "22",
      "FatherStepID": "1",
      "AbsoluteScheduledDate": "2017-02-13",
      "ScheduledTime": "01:09:37:00",
      "ScheduledDuration": "00:02:13:00",
      "NumPhase": 21,
      "Inclusion": 0,
      "NumEventCond": 22,
      "TypEvent": "Primary Event",
      "StartMode": "Follow",
      "PressTitle": "Festin de Balthazar op 51 reduction pour piano / integrale : Procession orientale",
      "BroadcastNature": "En différé",
      "TechnicalComment": "",
      "Intro1Duration": [
        "00:00:00:00",
        "00:00:00:00"
      ],
      "Intro1DurationMS": 0,
      "SoundId": "Titre de CD",
      "LongTitle": "Festin de Balthazar op 51 reduction pour piano / integrale : Procession orientale",
      "Label": "HANSSLER CLASSIC",
      "ReferenceLabel": "CD 98.261",
      "ExternalID": "4010276019114-1-13",
      "AlbumTitle": "Sibelius :Transcriptions pour piano",
      "Rank": 13,
      "NumVolume": 1,
      "PublicationDate": "2007-01-01",
      "LibMusicalKind": "Musique de chambre",
      "Instru": false,
      "SupportType": "Fichier",
      "CDBarCode": "4010276019114",
      "Compositor": {
        "Highlight": true,
        "FullName": "Jean Sibelius",
        "Profession": "Compositeur/Compositrice"
      },
      "Interpreter": {
        "FullName": "Henri Sigfridsson",
        "Profession": "Interprète",
        "InterventionNote": "Henri Sigfridsson : Piano",
        "mop": "Piano"
      },
      "ScheduledDateTime": "2017-02-13T01:09:37+01:00",
      "composer": "http://data.doremus.org/artist/72b3b303-5c15-319f-9c31-dc73b5b0fe74",
      "best": "http://data.doremus.org/expression/6085dc78-fd49-3066-bc50-9c62202c729e",
      "best_matching_score": "0.92"
    },
    {
      "id": "23",
      "StepID": "23",
      "FatherStepID": "1",
      "AbsoluteScheduledDate": "2017-02-13",
      "ScheduledTime": "01:11:50:00",
      "ScheduledDuration": "00:02:18:00",
      "NumPhase": 22,
      "Inclusion": 0,
      "NumEventCond": 23,
      "TypEvent": "Primary Event",
      "StartMode": "Follow",
      "PressTitle": "Cendrillon : Orientalia (acte III)",
      "BroadcastNature": "En différé",
      "TechnicalComment": "",
      "Intro1Duration": [
        "00:00:00:00",
        "00:00:00:00"
      ],
      "Intro1DurationMS": 0,
      "SoundId": "Titre de CD",
      "LongTitle": "Cendrillon : Orientalia (acte III)",
      "Label": "EMI CLASSICS",
      "ReferenceLabel": "5686042",
      "ExternalID": "0724356860421-2-13",
      "AlbumTitle": "Prokofiev : Cendrillon et Symphonie n°1",
      "Rank": 13,
      "NumVolume": 2,
      "LibMusicalKind": "Musique symphonique",
      "Instru": false,
      "SupportType": "Fichier",
      "CDBarCode": "0724356860421",
      "Compositor": {
        "Highlight": true,
        "FullName": "Serge Prokofiev",
        "Profession": "Compositeur/Compositrice"
      },
      "Orchestra": {
        "EntityName": "Orchestre Symphonique De Londres",
        "EntityType": "Orchestre"
      },
      "OrchestraLeader": {
        "FullName": "Andre Previn",
        "Profession": "Chef d'orchestre"
      },
      "ScheduledDateTime": "2017-02-13T01:11:50+01:00",
      "composer": "http://data.doremus.org/artist/47e04849-715e-3773-a2d1-a2ce2c7d320d",
      "best": "http://data.doremus.org/expression/09b3fc1e-5907-34b8-9358-081f51a852d0",
      "best_matching_score": "1.00"
    },
    {
      "id": "25",
      "StepID": "25",
      "FatherStepID": "1",
      "AbsoluteScheduledDate": "2017-02-13",
      "ScheduledTime": "01:14:12:00",
      "ScheduledDuration": "00:04:44:00",
      "NumPhase": 24,
      "Inclusion": 0,
      "NumEventCond": 25,
      "TypEvent": "Primary Event",
      "StartMode": "Follow",
      "PressTitle": "Danse orientale op 2 n°2",
      "BroadcastNature": "En différé",
      "TechnicalComment": "",
      "Intro1Duration": [
        "00:00:00:00",
        "00:00:00:00"
      ],
      "Intro1DurationMS": 0,
      "SoundId": "Titre de CD",
      "LongTitle": "Danse orientale op 2 n°2",
      "Label": "HANSSLER CLASSIC",
      "ReferenceLabel": "CD 93.245",
      "ExternalID": "4010276021995-1-2",
      "AlbumTitle": "Serge Rachmaninov : Oeuvres pour violoncelle et piano",
      "Rank": 2,
      "NumVolume": 1,
      "PublicationDate": "2009-01-01",
      "LibMusicalKind": "Musique de chambre",
      "Instru": false,
      "SupportType": "Fichier",
      "CDBarCode": "4010276021995",
      "Compositor": {
        "Highlight": true,
        "FullName": "Serge Rachmaninov",
        "Profession": "Compositeur/Compositrice"
      },
      "Interpreter": [
        {
          "FullName": "David Geringas",
          "Profession": "Interprète",
          "InterventionNote": "David Geringas : Violoncelle",
          "mop": "Violoncelle"
        },
        {
          "FullName": "Ian Foutain",
          "Profession": "Interprète",
          "InterventionNote": "Ian Foutain : Piano",
          "mop": "Piano"
        }
      ],
      "ScheduledDateTime": "2017-02-13T01:14:12+01:00",
      "composer": "http://data.doremus.org/artist/0ea76b7f-9eca-35c3-8e32-8ba22b19a96e"
    },
    {
      "id": "26",
      "StepID": "26",
      "FatherStepID": "1",
      "AbsoluteScheduledDate": "2017-02-13",
      "ScheduledTime": "01:18:56:00",
      "ScheduledDuration": "00:03:15:00",
      "NumPhase": 25,
      "Inclusion": 0,
      "NumEventCond": 26,
      "TypEvent": "Primary Event",
      "StartMode": "Follow",
      "PressTitle": "2 esquisses (intégrale) : Orientale",
      "BroadcastNature": "En différé",
      "TechnicalComment": "",
      "Intro1Duration": [
        "00:00:00:00",
        "00:00:00:00"
      ],
      "Intro1DurationMS": 0,
      "SoundId": "Titre de CD",
      "LongTitle": "2 esquisses (intégrale) : Orientale",
      "Label": "NAXOS",
      "ReferenceLabel": "8.5577307",
      "ExternalID": "0747313230723-1-2",
      "AlbumTitle": "Philippe Gaubert : Intégrale de l'oeuvre pour flûte traversière / Vol.3",
      "Rank": 2,
      "NumVolume": 1,
      "PublicationDate": "2006-01-01",
      "LibMusicalKind": "Musique de chambre",
      "Instru": false,
      "SupportType": "Fichier",
      "CDBarCode": "0747313230723",
      "Compositor": {
        "Highlight": true,
        "FullName": "Philippe Gaubert",
        "Profession": "Compositeur/Compositrice"
      },
      "Interpreter": [
        {
          "FullName": "Fenwick Smith",
          "Profession": "Interprète",
          "InterventionNote": "Fenwick Smith : Flûte traversière",
          "mop": "Flûte traversière"
        },
        {
          "FullName": "Sally Pinkas",
          "Profession": "Interprète",
          "InterventionNote": "Sally Pinkas : Piano",
          "mop": "Piano"
        }
      ],
      "ScheduledDateTime": "2017-02-13T01:18:56+01:00",
      "composer": "http://data.doremus.org/artist/7cc936c8-d22d-331d-8668-49b0767dd355"
    },
    {
      "id": "27",
      "StepID": "27",
      "FatherStepID": "1",
      "AbsoluteScheduledDate": "2017-02-13",
      "ScheduledTime": "01:22:11:00",
      "ScheduledDuration": "00:07:51:00",
      "NumPhase": 26,
      "Inclusion": 0,
      "NumEventCond": 27,
      "TypEvent": "Primary Event",
      "StartMode": "Follow",
      "PressTitle": "Colore orientale op 44 n°3",
      "BroadcastNature": "En différé",
      "TechnicalComment": "",
      "Intro1Duration": [
        "00:00:00:00",
        "00:00:00:00"
      ],
      "Intro1DurationMS": 0,
      "SoundId": "Titre de CD",
      "LongTitle": "Colore orientale op 44 n°3",
      "Label": "NAXOS",
      "ReferenceLabel": "8.570932",
      "ExternalID": "0747313093274-1-7",
      "AlbumTitle": "Intégrale de la musique orchestrale",
      "Rank": 7,
      "NumVolume": 1,
      "PublicationDate": "2009-01-01",
      "LibMusicalKind": "Musique symphonique",
      "Instru": false,
      "SupportType": "Fichier",
      "CDBarCode": "0747313093274",
      "Compositor": {
        "Highlight": true,
        "FullName": "Giuseppe Martucci",
        "Profession": "Compositeur/Compositrice"
      },
      "Orchestra": {
        "EntityName": "Orchestre Symphonique De Rome",
        "EntityType": "Orchestre"
      },
      "OrchestraLeader": {
        "FullName": "Francesco La Vecchia",
        "Profession": "Chef d'orchestre"
      },
      "ScheduledDateTime": "2017-02-13T01:22:11+01:00",
      "composer": "http://data.doremus.org/artist/28a40c43-285d-32bd-bf71-939159718868"
    },
    {
      "id": "28",
      "StepID": "28",
      "FatherStepID": "1",
      "AbsoluteScheduledDate": "2017-02-13",
      "ScheduledTime": "01:30:02:00",
      "ScheduledDuration": "00:08:11:00",
      "NumPhase": 27,
      "Inclusion": 0,
      "NumEventCond": 28,
      "TypEvent": "Primary Event",
      "StartMode": "Follow",
      "PressTitle": "La captive op 12 - pour mezzo-soprano et orchestre",
      "BroadcastNature": "En différé",
      "TechnicalComment": "",
      "Intro1Duration": [
        "00:00:00:00",
        "00:00:00:00"
      ],
      "Intro1DurationMS": 0,
      "SoundId": "Titre de CD",
      "LongTitle": "La captive op 12 - pour mezzo-soprano et orchestre",
      "Label": "EMI CLASSICS",
      "ReferenceLabel": "9038042",
      "ExternalID": "RF00000043887-1-23",
      "AlbumTitle": "Janet Baker interprète Duparc Fauré Debussy et autres compositeurs / CD 17",
      "Rank": 23,
      "NumVolume": 1,
      "PublicationDate": "2013-01-01",
      "LibMusicalKind": "Musique chorale et vocale",
      "Instru": false,
      "SupportType": "Fichier",
      "CDBarCode": "RF00000043887",
      "Compositor": {
        "Highlight": true,
        "FullName": "Hector Berlioz",
        "Profession": "Compositeur/Compositrice"
      },
      "Interpreter": {
        "FullName": "Janet Baker",
        "Profession": "Interprète",
        "InterventionNote": "Janet Baker : Mezzo-soprano",
        "mop": "Mezzo-soprano"
      },
      "Orchestra": {
        "EntityName": "City Of London Sinfonia",
        "EntityType": "Orchestre"
      },
      "OrchestraLeader": {
        "FullName": "Richard Hickox",
        "Profession": "Chef d'orchestre"
      },
      "ScheduledDateTime": "2017-02-13T01:30:02+01:00",
      "composer": "http://data.doremus.org/artist/69896139-4b18-30ff-bc65-7c14e18f1707",
      "best": "http://data.doremus.org/expression/4b233007-82de-32b8-a7a9-e82b9cf20aac",
      "best_matching_score": "1.00"
    },
    {
      "id": "30",
      "StepID": "30",
      "FatherStepID": "1",
      "AbsoluteScheduledDate": "2017-02-13",
      "ScheduledTime": "01:38:25:00",
      "ScheduledDuration": "00:04:35:00",
      "NumPhase": 29,
      "Inclusion": 0,
      "NumEventCond": 30,
      "TypEvent": "Primary Event",
      "StartMode": "Follow",
      "PressTitle": "5 novelettes op 15 : Interludium in modo antico - Novelette op 15 n°3 / Interlude dans la style ancien",
      "BroadcastNature": "En différé",
      "TechnicalComment": "",
      "Intro1Duration": [
        "00:00:00:00",
        "00:00:00:00"
      ],
      "Intro1DurationMS": 0,
      "SoundId": "Titre de CD",
      "LongTitle": "5 novelettes op 15 : Interludium in modo antico - Novelette op 15 n°3 / Interlude dans la style ancien",
      "Label": "OLYMPIA",
      "ReferenceLabel": "OCD 524",
      "ExternalID": "5015524405243-1-11",
      "AlbumTitle": "Glinka et Glazounov : Quatuor à cordes / Vol.4",
      "Rank": 11,
      "NumVolume": 1,
      "LibMusicalKind": "Musique de chambre",
      "Instru": false,
      "SupportType": "Fichier",
      "CDBarCode": "5015524405243",
      "Compositor": {
        "Highlight": true,
        "FullName": "Alexandre Glazounov",
        "Profession": "Compositeur/Compositrice"
      },
      "Interpreter": [
        {
          "FullName": "Quatuor Chostakovitch",
          "Profession": "Interprète",
          "InterventionNote": "Quatuor Chostakovitch"
        },
        {
          "FullName": "Andrei Shishlov",
          "Profession": "Interprète",
          "InterventionNote": "Andrei Shishlov : Violon",
          "mop": "Violon"
        },
        {
          "FullName": "Alexander Balashov",
          "Profession": "Interprète",
          "InterventionNote": "Alexander Balashov : Violon",
          "mop": "Violon"
        },
        {
          "FullName": "Alexander Galkovski",
          "Profession": "Interprète",
          "InterventionNote": "Alexander Galkovski : Alto (instrument)",
          "mop": "Alto (instrument)"
        },
        {
          "FullName": "Alexander Korchagin",
          "Profession": "Interprète",
          "InterventionNote": "Alexander Korchagin : Violoncelle",
          "mop": "Violoncelle"
        }
      ],
      "ScheduledDateTime": "2017-02-13T01:38:25+01:00",
      "composer": "http://data.doremus.org/artist/064a15a4-b08d-3300-9b18-91ca4e79671c"
    },
    {
      "id": "31",
      "StepID": "31",
      "FatherStepID": "1",
      "AbsoluteScheduledDate": "2017-02-13",
      "ScheduledTime": "01:43:00:00",
      "ScheduledDuration": "00:03:59:00",
      "NumPhase": 30,
      "Inclusion": 0,
      "NumEventCond": 31,
      "TypEvent": "Primary Event",
      "StartMode": "Follow",
      "PressTitle": "Suite dans le style ancien en Ré Maj op 24 : Menuet - version pour trompette 2 flûtes traversières et orchestre à cordes",
      "BroadcastNature": "En différé",
      "TechnicalComment": "",
      "Intro1Duration": [
        "00:00:00:00",
        "00:00:00:00"
      ],
      "Intro1DurationMS": 0,
      "SoundId": "Titre de CD",
      "LongTitle": "Suite dans le style ancien en Ré Maj op 24 : Menuet - version pour trompette 2 flûtes traversières et orchestre à cordes",
      "Label": "CHANDOS",
      "ReferenceLabel": "CHSA5157",
      "ExternalID": "0095115515723-1-16",
      "AlbumTitle": "Vincent d'Indy : Oeuvres orchestrales / Vol.6",
      "Rank": 16,
      "NumVolume": 1,
      "PublicationDate": "2015-01-01",
      "LibMusicalKind": "Musique symphonique",
      "Instru": false,
      "SupportType": "Fichier",
      "CDBarCode": "0095115515723",
      "Compositor": {
        "Highlight": true,
        "FullName": "Vincent D'Indy",
        "Profession": "Compositeur/Compositrice"
      },
      "Orchestra": {
        "EntityName": "Orchestre Symphonique D'Islande",
        "EntityType": "Orchestre"
      },
      "OrchestraLeader": {
        "FullName": "Rumon Gamba",
        "Profession": "Chef d'orchestre"
      },
      "ScheduledDateTime": "2017-02-13T01:43:00+01:00",
      "composer": "http://data.doremus.org/artist/ece1cb94-29b1-3ae8-bd23-f2d2f7cbf68d"
    },
    {
      "id": "32",
      "StepID": "32",
      "FatherStepID": "1",
      "AbsoluteScheduledDate": "2017-02-13",
      "ScheduledTime": "01:46:59:00",
      "ScheduledDuration": "00:03:32:00",
      "NumPhase": 31,
      "Inclusion": 0,
      "NumEventCond": 32,
      "TypEvent": "Primary Event",
      "StartMode": "Follow",
      "PressTitle": "Suite dans le style ancien en Ré Maj op 24 : Ronde française - version pour trompette 2 flûtes traversières et orchestre à cordes",
      "BroadcastNature": "En différé",
      "TechnicalComment": "",
      "Intro1Duration": [
        "00:00:00:00",
        "00:00:00:00"
      ],
      "Intro1DurationMS": 0,
      "SoundId": "Titre de CD",
      "LongTitle": "Suite dans le style ancien en Ré Maj op 24 : Ronde française - version pour trompette 2 flûtes traversières et orchestre à cordes",
      "Label": "CHANDOS",
      "ReferenceLabel": "CHSA5157",
      "ExternalID": "0095115515723-1-17",
      "AlbumTitle": "Vincent d'Indy : Oeuvres orchestrales / Vol.6",
      "Rank": 17,
      "NumVolume": 1,
      "PublicationDate": "2015-01-01",
      "LibMusicalKind": "Musique symphonique",
      "Instru": false,
      "SupportType": "Fichier",
      "CDBarCode": "0095115515723",
      "Compositor": {
        "Highlight": true,
        "FullName": "Vincent D'Indy",
        "Profession": "Compositeur/Compositrice"
      },
      "Orchestra": {
        "EntityName": "Orchestre Symphonique D'Islande",
        "EntityType": "Orchestre"
      },
      "OrchestraLeader": {
        "FullName": "Rumon Gamba",
        "Profession": "Chef d'orchestre"
      },
      "ScheduledDateTime": "2017-02-13T01:46:59+01:00",
      "composer": "http://data.doremus.org/artist/ece1cb94-29b1-3ae8-bd23-f2d2f7cbf68d"
    },
    {
      "id": "33",
      "StepID": "33",
      "FatherStepID": "1",
      "AbsoluteScheduledDate": "2017-02-13",
      "ScheduledTime": "01:50:31:00",
      "ScheduledDuration": "00:04:06:00",
      "NumPhase": 32,
      "Inclusion": 0,
      "NumEventCond": 33,
      "TypEvent": "Primary Event",
      "StartMode": "Follow",
      "PressTitle": "Au temps de Holberg op 40 : Rigaudon - suite dans le style ancien pour piano",
      "BroadcastNature": "En différé",
      "TechnicalComment": "",
      "Intro1Duration": [
        "00:00:00:00",
        "00:00:00:00"
      ],
      "Intro1DurationMS": 0,
      "SoundId": "Titre de CD",
      "LongTitle": "Au temps de Holberg op 40 : Rigaudon - suite dans le style ancien pour piano",
      "Label": "GRAVE",
      "ReferenceLabel": "GRCD 2",
      "ExternalID": "3356578300781-1-6",
      "AlbumTitle": "Recital : Anne Kaasa joue Grieg",
      "Rank": 6,
      "NumVolume": 1,
      "LibMusicalKind": "Musique de chambre",
      "Instru": false,
      "SupportType": "Fichier",
      "CDBarCode": "3356578300781",
      "Compositor": {
        "Highlight": true,
        "FullName": "Edouard Grieg",
        "Profession": "Compositeur/Compositrice"
      },
      "Interpreter": {
        "FullName": "Anne Kaasa",
        "Profession": "Interprète",
        "InterventionNote": "Anne Kaasa : Piano",
        "mop": "Piano"
      },
      "ScheduledDateTime": "2017-02-13T01:50:31+01:00",
      "composer": "http://data.doremus.org/artist/182eb912-5a5b-3082-9008-9d46d47548ca",
      "best": "http://data.doremus.org/expression/0b9841c7-2fed-3ac7-bcdc-690f063de6d1",
      "best_matching_score": "0.96"
    },
    {
      "id": "34",
      "StepID": "34",
      "FatherStepID": "1",
      "AbsoluteScheduledDate": "2017-02-13",
      "ScheduledTime": "01:54:37:00",
      "ScheduledDuration": "00:01:59:00",
      "NumPhase": 33,
      "Inclusion": 0,
      "NumEventCond": 34,
      "TypEvent": "Primary Event",
      "StartMode": "Follow",
      "PressTitle": "Suite im alten Stil op 10 \"\"Suite dans un style ancien op 10\"\" - pour violon et piano : 1 - Presto",
      "BroadcastNature": "En différé",
      "TechnicalComment": "",
      "Intro1Duration": [
        "00:00:00:00",
        "00:00:00:00"
      ],
      "Intro1DurationMS": 0,
      "SoundId": "Titre de CD",
      "LongTitle": "Suite im alten Stil op 10 \"\"Suite dans un style ancien op 10\"\" - pour violon et piano : 1 - Presto",
      "Label": "NAXOS",
      "ReferenceLabel": "8.572254",
      "ExternalID": "0747313225477-1-7",
      "AlbumTitle": "Musique pour violon et piano",
      "Rank": 7,
      "NumVolume": 1,
      "PublicationDate": "2008-01-01",
      "LibMusicalKind": "Musique de chambre",
      "Instru": false,
      "SupportType": "Fichier",
      "CDBarCode": "0747313225477",
      "Compositor": {
        "Highlight": true,
        "FullName": "Christian Sinding",
        "Profession": "Compositeur/Compositrice"
      },
      "Interpreter": [
        {
          "FullName": "Henning Kristofer Kraggerud",
          "Profession": "Interprète",
          "InterventionNote": "Henning Kristofer Kraggerud : Violon",
          "mop": "Violon"
        },
        {
          "FullName": "Christian Ihle Hadland",
          "Profession": "Interprète",
          "InterventionNote": "Christian Ihle Hadland : Piano",
          "mop": "Piano"
        }
      ],
      "ScheduledDateTime": "2017-02-13T01:54:37+01:00",
      "composer": "http://data.doremus.org/artist/55522f09-699b-383b-9cd7-82e73f6b18da",
      "best": "http://data.doremus.org/expression/36a27904-638c-31c9-9842-2cbda0aeb4e9",
      "best_matching_score": "0.93"
    },
    {
      "id": "35",
      "StepID": "35",
      "FatherStepID": "1",
      "AbsoluteScheduledDate": "2017-02-13",
      "ScheduledTime": "01:56:36:00",
      "ScheduledDuration": "00:05:58:00",
      "NumPhase": 34,
      "Inclusion": 0,
      "NumEventCond": 35,
      "TypEvent": "Primary Event",
      "StartMode": "Follow",
      "PressTitle": "Suite im alten Stil op 10 \"\"Suite dans un style ancien op 10\"\" - pour violon et piano : 2 - Adagio",
      "BroadcastNature": "En différé",
      "TechnicalComment": "",
      "Intro1Duration": [
        "00:00:00:00",
        "00:00:00:00"
      ],
      "Intro1DurationMS": 0,
      "SoundId": "Titre de CD",
      "LongTitle": "Suite im alten Stil op 10 \"\"Suite dans un style ancien op 10\"\" - pour violon et piano : 2 - Adagio",
      "Label": "NAXOS",
      "ReferenceLabel": "8.572254",
      "ExternalID": "0747313225477-1-8",
      "AlbumTitle": "Musique pour violon et piano",
      "Rank": 8,
      "NumVolume": 1,
      "PublicationDate": "2008-01-01",
      "LibMusicalKind": "Musique de chambre",
      "Instru": false,
      "SupportType": "Fichier",
      "CDBarCode": "0747313225477",
      "Compositor": {
        "Highlight": true,
        "FullName": "Christian Sinding",
        "Profession": "Compositeur/Compositrice"
      },
      "Interpreter": [
        {
          "FullName": "Henning Kristofer Kraggerud",
          "Profession": "Interprète",
          "InterventionNote": "Henning Kristofer Kraggerud : Violon",
          "mop": "Violon"
        },
        {
          "FullName": "Christian Ihle Hadland",
          "Profession": "Interprète",
          "InterventionNote": "Christian Ihle Hadland : Piano",
          "mop": "Piano"
        }
      ],
      "ScheduledDateTime": "2017-02-13T01:56:36+01:00",
      "composer": "http://data.doremus.org/artist/55522f09-699b-383b-9cd7-82e73f6b18da",
      "best": "http://data.doremus.org/expression/36a27904-638c-31c9-9842-2cbda0aeb4e9",
      "best_matching_score": "0.93"
    },
    {
      "id": "37",
      "StepID": "37",
      "FatherStepID": "1",
      "AbsoluteScheduledDate": "2017-02-13",
      "ScheduledTime": "02:02:43:00",
      "ScheduledDuration": "00:02:22:00",
      "NumPhase": 36,
      "Inclusion": 0,
      "NumEventCond": 37,
      "TypEvent": "Primary Event",
      "StartMode": "Follow",
      "PressTitle": "Suite d'apres le roi pinard : V - rondeau dans le style ancien / Suite pour orchestre arrangee d'apres l'operette / Integrale",
      "BroadcastNature": "En différé",
      "TechnicalComment": "",
      "Intro1Duration": [
        "00:00:00:00",
        "00:00:00:00"
      ],
      "Intro1DurationMS": 0,
      "SoundId": "Titre de CD",
      "LongTitle": "Suite d'apres le roi pinard : V - rondeau dans le style ancien / Suite pour orchestre arrangee d'apres l'operette / Integrale",
      "Label": "LES PRODUCTIONS RSR",
      "ReferenceLabel": "RSR 6197",
      "ExternalID": "7611745061978-1-14",
      "AlbumTitle": "Oeuvres pour orchestre",
      "Rank": 14,
      "NumVolume": 1,
      "LibMusicalKind": "Musique symphonique",
      "Instru": false,
      "SupportType": "Fichier",
      "CDBarCode": "7611745061978",
      "Compositor": {
        "Highlight": true,
        "FullName": "Deodat De Severac",
        "Profession": "Compositeur/Compositrice"
      },
      "Interpreter": {
        "FullName": "Jael Azzaretti",
        "Profession": "Interprète",
        "InterventionNote": "Jael Azzaretti : Soprano",
        "mop": "Soprano"
      },
      "Orchestra": {
        "EntityName": "Orchestre De La Suisse Romande",
        "EntityType": "Orchestre"
      },
      "Choir": [
        {
          "EntityName": "Ching Lien",
          "EntityType": "Choeur"
        },
        {
          "EntityName": "Non Identifie",
          "EntityType": "Choeur"
        }
      ],
      "OrchestraLeader": {
        "FullName": "Roberto Benzi",
        "Profession": "Chef d'orchestre"
      },
      "ScheduledDateTime": "2017-02-13T02:02:43+01:00",
      "composer": "http://data.doremus.org/artist/5dc75a67-7470-3c2b-9703-a804e3a881d5"
    },
    {
      "id": "38",
      "StepID": "38",
      "FatherStepID": "1",
      "AbsoluteScheduledDate": "2017-02-13",
      "ScheduledTime": "02:05:05:00",
      "ScheduledDuration": "00:03:41:00",
      "NumPhase": 37,
      "Inclusion": 0,
      "NumEventCond": 38,
      "TypEvent": "Primary Event",
      "StartMode": "Follow",
      "PressTitle": "Ein Tanzspiel : Sarabande - pour orchestre dans le style ancien",
      "BroadcastNature": "En différé",
      "TechnicalComment": "",
      "Intro1Duration": [
        "00:00:00:00",
        "00:00:00:00"
      ],
      "Intro1DurationMS": 0,
      "SoundId": "Titre de CD",
      "LongTitle": "Ein Tanzspiel : Sarabande - pour orchestre dans le style ancien",
      "Label": "NIMBUS",
      "ReferenceLabel": "NI 5753",
      "ExternalID": "0710357575327-1-18",
      "AlbumTitle": "Franz Schreker et L'Ausdruckstanz",
      "Rank": 18,
      "NumVolume": 1,
      "PublicationDate": "2005-01-01",
      "LibMusicalKind": "Musique symphonique",
      "Instru": false,
      "SupportType": "Fichier",
      "CDBarCode": "0710357575327",
      "Compositor": {
        "Highlight": true,
        "FullName": "Franz Schreker",
        "Profession": "Compositeur/Compositrice"
      },
      "Orchestra": {
        "EntityName": "Orchestre Symphonique De Lucerne",
        "EntityType": "Orchestre"
      },
      "OrchestraLeader": {
        "FullName": "John Axelrod",
        "Profession": "Chef d'orchestre"
      },
      "ScheduledDateTime": "2017-02-13T02:05:05+01:00",
      "composer": "http://data.doremus.org/artist/868baf0f-058c-3db9-a72a-6a2a3ce3dd37",
      "best": "http://data.doremus.org/expression/86b2fac3-641c-33ec-a28d-5d09c23da03d",
      "best_matching_score": "1.00"
    },
    {
      "id": "39",
      "StepID": "39",
      "FatherStepID": "1",
      "AbsoluteScheduledDate": "2017-02-13",
      "ScheduledTime": "02:08:46:00",
      "ScheduledDuration": "00:02:49:00",
      "NumPhase": 38,
      "Inclusion": 0,
      "NumEventCond": 39,
      "TypEvent": "Primary Event",
      "StartMode": "Follow",
      "PressTitle": "Ein Tanzspiel : Menuet - pour orchestre dans le style ancien",
      "BroadcastNature": "En différé",
      "TechnicalComment": "",
      "Intro1Duration": [
        "00:00:00:00",
        "00:00:00:00"
      ],
      "Intro1DurationMS": 0,
      "SoundId": "Titre de CD",
      "LongTitle": "Ein Tanzspiel : Menuet - pour orchestre dans le style ancien",
      "Label": "NIMBUS",
      "ReferenceLabel": "NI 5753",
      "ExternalID": "0710357575327-1-19",
      "AlbumTitle": "Franz Schreker et L'Ausdruckstanz",
      "Rank": 19,
      "NumVolume": 1,
      "PublicationDate": "2005-01-01",
      "LibMusicalKind": "Musique symphonique",
      "Instru": false,
      "SupportType": "Fichier",
      "CDBarCode": "0710357575327",
      "Compositor": {
        "Highlight": true,
        "FullName": "Franz Schreker",
        "Profession": "Compositeur/Compositrice"
      },
      "Orchestra": {
        "EntityName": "Orchestre Symphonique De Lucerne",
        "EntityType": "Orchestre"
      },
      "OrchestraLeader": {
        "FullName": "John Axelrod",
        "Profession": "Chef d'orchestre"
      },
      "ScheduledDateTime": "2017-02-13T02:08:46+01:00",
      "composer": "http://data.doremus.org/artist/868baf0f-058c-3db9-a72a-6a2a3ce3dd37",
      "best": "http://data.doremus.org/expression/86b2fac3-641c-33ec-a28d-5d09c23da03d",
      "best_matching_score": "1.00"
    },
    {
      "id": "40",
      "StepID": "40",
      "FatherStepID": "1",
      "AbsoluteScheduledDate": "2017-02-13",
      "ScheduledTime": "02:11:35:00",
      "ScheduledDuration": "00:03:06:00",
      "NumPhase": 39,
      "Inclusion": 0,
      "NumEventCond": 40,
      "TypEvent": "Primary Event",
      "StartMode": "Follow",
      "PressTitle": "Danses et airs antiques : Suite n°3 : Siciliana - pour orchestre à cordes",
      "BroadcastNature": "En différé",
      "TechnicalComment": "",
      "Intro1Duration": [
        "00:00:00:00",
        "00:00:00:00"
      ],
      "Intro1DurationMS": 0,
      "SoundId": "Titre de CD",
      "LongTitle": "Danses et airs antiques : Suite n°3 : Siciliana - pour orchestre à cordes",
      "Label": "MERCURY",
      "ReferenceLabel": "416496-2",
      "ExternalID": "0028941649621-1-17",
      "AlbumTitle": "Ottorino Respighi : Danses et airs antiques",
      "Rank": 17,
      "NumVolume": 1,
      "LibMusicalKind": "Musique symphonique",
      "Instru": false,
      "SupportType": "Fichier",
      "CDBarCode": "0028941649621",
      "Compositor": [
        {
          "Highlight": true,
          "FullName": "Ottorino Respighi",
          "Profession": "Compositeur/Compositrice"
        },
        {
          "FullName": "Anonyme",
          "Profession": "Compositeur/Compositrice"
        }
      ],
      "Orchestra": {
        "EntityName": "Philharmonia Hungarica",
        "EntityType": "Orchestre"
      },
      "OrchestraLeader": {
        "FullName": "Antal Dorati",
        "Profession": "Chef d'orchestre"
      },
      "ScheduledDateTime": "2017-02-13T02:11:35+01:00"
    },
    {
      "id": "41",
      "StepID": "41",
      "FatherStepID": "1",
      "AbsoluteScheduledDate": "2017-02-13",
      "ScheduledTime": "02:14:41:00",
      "ScheduledDuration": "00:05:33:00",
      "NumPhase": 40,
      "Inclusion": 0,
      "NumEventCond": 41,
      "TypEvent": "Primary Event",
      "StartMode": "Follow",
      "PressTitle": "5 novelettes op 15 : Valse - Novelette op 15 n°4",
      "BroadcastNature": "En différé",
      "TechnicalComment": "",
      "Intro1Duration": [
        "00:00:00:00",
        "00:00:00:00"
      ],
      "Intro1DurationMS": 0,
      "SoundId": "Titre de CD",
      "LongTitle": "5 novelettes op 15 : Valse - Novelette op 15 n°4",
      "Label": "OLYMPIA",
      "ReferenceLabel": "OCD 524",
      "ExternalID": "5015524405243-1-12",
      "AlbumTitle": "Glinka et Glazounov : Quatuor à cordes / Vol.4",
      "Rank": 12,
      "NumVolume": 1,
      "LibMusicalKind": "Musique de chambre",
      "Instru": false,
      "SupportType": "Fichier",
      "CDBarCode": "5015524405243",
      "Compositor": {
        "Highlight": true,
        "FullName": "Alexandre Glazounov",
        "Profession": "Compositeur/Compositrice"
      },
      "Interpreter": [
        {
          "FullName": "Quatuor Chostakovitch",
          "Profession": "Interprète",
          "InterventionNote": "Quatuor Chostakovitch"
        },
        {
          "FullName": "Andrei Shishlov",
          "Profession": "Interprète",
          "InterventionNote": "Andrei Shishlov : Violon",
          "mop": "Violon"
        },
        {
          "FullName": "Alexander Balashov",
          "Profession": "Interprète",
          "InterventionNote": "Alexander Balashov : Violon",
          "mop": "Violon"
        },
        {
          "FullName": "Alexander Galkovski",
          "Profession": "Interprète",
          "InterventionNote": "Alexander Galkovski : Alto (instrument)",
          "mop": "Alto (instrument)"
        },
        {
          "FullName": "Alexander Korchagin",
          "Profession": "Interprète",
          "InterventionNote": "Alexander Korchagin : Violoncelle",
          "mop": "Violoncelle"
        }
      ],
      "ScheduledDateTime": "2017-02-13T02:14:41+01:00",
      "composer": "http://data.doremus.org/artist/064a15a4-b08d-3300-9b18-91ca4e79671c"
    },
    {
      "id": "43",
      "StepID": "43",
      "FatherStepID": "1",
      "AbsoluteScheduledDate": "2017-02-13",
      "ScheduledTime": "02:20:26:00",
      "ScheduledDuration": "00:01:36:00",
      "NumPhase": 42,
      "Inclusion": 0,
      "NumEventCond": 43,
      "TypEvent": "Primary Event",
      "StartMode": "Follow",
      "PressTitle": "6 Walzer-Gesänge nach toskanischen Volksliedern op 6 : Liebe Schwalbe op 6 n°1",
      "BroadcastNature": "En différé",
      "TechnicalComment": "",
      "Intro1Duration": [
        "00:00:00:00",
        "00:00:00:00"
      ],
      "Intro1DurationMS": 0,
      "SoundId": "Titre de CD",
      "LongTitle": "6 Walzer-Gesänge nach toskanischen Volksliedern op 6 : Liebe Schwalbe op 6 n°1",
      "Label": "APARTE",
      "ReferenceLabel": "AP054",
      "ExternalID": "3149028031621-1-8",
      "AlbumTitle": "Art nouveau",
      "Rank": 8,
      "NumVolume": 1,
      "PublicationDate": "2011-01-01",
      "LibMusicalKind": "Musique chorale et vocale",
      "Instru": false,
      "SupportType": "Fichier",
      "CDBarCode": "3149028031621",
      "Compositor": {
        "Highlight": true,
        "FullName": "Alexander Von Zemlinsky",
        "Profession": "Compositeur/Compositrice"
      },
      "Interpreter": [
        {
          "FullName": "Teodora Gheorghiu",
          "Profession": "Interprète",
          "InterventionNote": "Teodora Gheorghiu : Soprano",
          "mop": "Soprano"
        },
        {
          "FullName": "Jonathan Aner",
          "Profession": "Interprète",
          "InterventionNote": "Jonathan Aner : Piano",
          "mop": "Piano"
        }
      ],
      "ScheduledDateTime": "2017-02-13T02:20:26+01:00",
      "composer": "http://data.doremus.org/artist/2f1020fd-60ac-3b4d-9290-5bae9c611efd",
      "best": "http://data.doremus.org/expression/bda3056e-f5b1-3813-80ba-5cce6f3fd5d4",
      "best_matching_score": "0.96"
    },
    {
      "id": "44",
      "StepID": "44",
      "FatherStepID": "1",
      "AbsoluteScheduledDate": "2017-02-13",
      "ScheduledTime": "02:22:02:00",
      "ScheduledDuration": "00:03:05:00",
      "NumPhase": 43,
      "Inclusion": 0,
      "NumEventCond": 44,
      "TypEvent": "Primary Event",
      "StartMode": "Follow",
      "PressTitle": "Acte 1 : Valse",
      "BroadcastNature": "En différé",
      "TechnicalComment": "",
      "Intro1Duration": [
        "00:00:00:00",
        "00:00:00:00"
      ],
      "Intro1DurationMS": 0,
      "SoundId": "Titre de CD",
      "LongTitle": "Acte 1 : Valse",
      "Label": "SONY",
      "ReferenceLabel": "SK 42450",
      "ExternalID": "5099704245027-1-7",
      "AlbumTitle": "Adam / Giselle / Tilson",
      "Rank": 7,
      "NumVolume": 1,
      "PublicationDate": "1987-01-01",
      "LibMusicalKind": "Musique symphonique",
      "Instru": false,
      "SupportType": "Fichier",
      "CDBarCode": "5099704245027",
      "Compositor": {
        "Highlight": true,
        "FullName": "Adolphe Adam",
        "Profession": "Compositeur/Compositrice"
      },
      "Orchestra": {
        "EntityName": "Orchestre Symphonique De Londres",
        "EntityType": "Orchestre"
      },
      "OrchestraLeader": {
        "FullName": "Michael Tilson-Thomas",
        "Profession": "Chef d'orchestre"
      },
      "ScheduledDateTime": "2017-02-13T02:22:02+01:00",
      "composer": "http://data.doremus.org/artist/6cf3d2d5-2ba6-3db1-8447-9764a8335486"
    },
    {
      "id": "45",
      "StepID": "45",
      "FatherStepID": "1",
      "AbsoluteScheduledDate": "2017-02-13",
      "ScheduledTime": "02:25:07:00",
      "ScheduledDuration": "00:00:56:00",
      "NumPhase": 44,
      "Inclusion": 0,
      "NumEventCond": 45,
      "TypEvent": "Primary Event",
      "StartMode": "Follow",
      "PressTitle": "6 Walzer-Gesänge nach toskanischen Volksliedern op 6 : Ich geh' des Nachts op 6 n°4",
      "BroadcastNature": "En différé",
      "TechnicalComment": "",
      "Intro1Duration": [
        "00:00:00:00",
        "00:00:00:00"
      ],
      "Intro1DurationMS": 0,
      "SoundId": "Titre de CD",
      "LongTitle": "6 Walzer-Gesänge nach toskanischen Volksliedern op 6 : Ich geh' des Nachts op 6 n°4",
      "Label": "APARTE",
      "ReferenceLabel": "AP054",
      "ExternalID": "3149028031621-1-11",
      "AlbumTitle": "Art nouveau",
      "Rank": 11,
      "NumVolume": 1,
      "PublicationDate": "2011-01-01",
      "LibMusicalKind": "Musique chorale et vocale",
      "Instru": false,
      "SupportType": "Fichier",
      "CDBarCode": "3149028031621",
      "Compositor": {
        "Highlight": true,
        "FullName": "Alexander Von Zemlinsky",
        "Profession": "Compositeur/Compositrice"
      },
      "Interpreter": [
        {
          "FullName": "Teodora Gheorghiu",
          "Profession": "Interprète",
          "InterventionNote": "Teodora Gheorghiu : Soprano",
          "mop": "Soprano"
        },
        {
          "FullName": "Jonathan Aner",
          "Profession": "Interprète",
          "InterventionNote": "Jonathan Aner : Piano",
          "mop": "Piano"
        }
      ],
      "ScheduledDateTime": "2017-02-13T02:25:07+01:00",
      "composer": "http://data.doremus.org/artist/2f1020fd-60ac-3b4d-9290-5bae9c611efd",
      "best": "http://data.doremus.org/expression/bda3056e-f5b1-3813-80ba-5cce6f3fd5d4",
      "best_matching_score": "0.96"
    },
    {
      "id": "46",
      "StepID": "46",
      "FatherStepID": "1",
      "AbsoluteScheduledDate": "2017-02-13",
      "ScheduledTime": "02:26:03:00",
      "ScheduledDuration": "00:06:01:00",
      "NumPhase": 45,
      "Inclusion": 0,
      "NumEventCond": 46,
      "TypEvent": "Primary Event",
      "StartMode": "Follow",
      "PressTitle": "Symphonie n°5 en mi min op 64 : valse : allegro moderato",
      "BroadcastNature": "En différé",
      "TechnicalComment": "",
      "Intro1Duration": [
        "00:00:00:00",
        "00:00:00:00"
      ],
      "Intro1DurationMS": 0,
      "SoundId": "Titre de CD",
      "LongTitle": "Symphonie n°5 en mi min op 64 : valse : allegro moderato",
      "Label": "XCP",
      "ReferenceLabel": "CD-HJS 2008",
      "ExternalID": "RF00000018141-1-6",
      "AlbumTitle": "Adrian Mac Donnell dirige Tchaikovsky et Schubnel",
      "Rank": 6,
      "NumVolume": 1,
      "LibMusicalKind": "Musique symphonique",
      "Instru": false,
      "SupportType": "Fichier",
      "CDBarCode": "RF00000018141",
      "Compositor": {
        "Highlight": true,
        "FullName": "Peter Illich Tchaikovsky",
        "Profession": "Compositeur/Compositrice"
      },
      "Orchestra": {
        "EntityName": "Orchestre De La Cite Internationale",
        "EntityType": "Orchestre"
      },
      "OrchestraLeader": {
        "FullName": "Adrian Mac Donnell",
        "Profession": "Chef d'orchestre"
      },
      "ScheduledDateTime": "2017-02-13T02:26:03+01:00"
    },
    {
      "id": "47",
      "StepID": "47",
      "FatherStepID": "1",
      "AbsoluteScheduledDate": "2017-02-13",
      "ScheduledTime": "02:32:04:00",
      "ScheduledDuration": "00:01:54:00",
      "NumPhase": 46,
      "Inclusion": 0,
      "NumEventCond": 47,
      "TypEvent": "Primary Event",
      "StartMode": "Follow",
      "PressTitle": "6 Walzer-Gesänge nach toskanischen Volksliedern op 6 : Blaues Sterlein op 6 n°5",
      "BroadcastNature": "En différé",
      "TechnicalComment": "",
      "Intro1Duration": [
        "00:00:00:00",
        "00:00:00:00"
      ],
      "Intro1DurationMS": 0,
      "SoundId": "Titre de CD",
      "LongTitle": "6 Walzer-Gesänge nach toskanischen Volksliedern op 6 : Blaues Sterlein op 6 n°5",
      "Label": "APARTE",
      "ReferenceLabel": "AP054",
      "ExternalID": "3149028031621-1-12",
      "AlbumTitle": "Art nouveau",
      "Rank": 12,
      "NumVolume": 1,
      "PublicationDate": "2011-01-01",
      "LibMusicalKind": "Musique chorale et vocale",
      "Instru": false,
      "SupportType": "Fichier",
      "CDBarCode": "3149028031621",
      "Compositor": {
        "Highlight": true,
        "FullName": "Alexander Von Zemlinsky",
        "Profession": "Compositeur/Compositrice"
      },
      "Interpreter": [
        {
          "FullName": "Teodora Gheorghiu",
          "Profession": "Interprète",
          "InterventionNote": "Teodora Gheorghiu : Soprano",
          "mop": "Soprano"
        },
        {
          "FullName": "Jonathan Aner",
          "Profession": "Interprète",
          "InterventionNote": "Jonathan Aner : Piano",
          "mop": "Piano"
        }
      ],
      "ScheduledDateTime": "2017-02-13T02:32:04+01:00",
      "composer": "http://data.doremus.org/artist/2f1020fd-60ac-3b4d-9290-5bae9c611efd",
      "best": "http://data.doremus.org/expression/bda3056e-f5b1-3813-80ba-5cce6f3fd5d4",
      "best_matching_score": "0.97"
    },
    {
      "id": "49",
      "StepID": "49",
      "FatherStepID": "1",
      "AbsoluteScheduledDate": "2017-02-13",
      "ScheduledTime": "02:34:02:00",
      "ScheduledDuration": "00:08:20:00",
      "NumPhase": 48,
      "Inclusion": 0,
      "NumEventCond": 49,
      "TypEvent": "Primary Event",
      "StartMode": "Follow",
      "PressTitle": "Novelettes op 15 : All' ungherese",
      "BroadcastNature": "En différé",
      "TechnicalComment": "",
      "Intro1Duration": [
        "00:00:00:00",
        "00:00:00:00"
      ],
      "Intro1DurationMS": 0,
      "SoundId": "Titre de CD",
      "LongTitle": "Novelettes op 15 : All' ungherese",
      "Label": "MDG",
      "ReferenceLabel": "MDG 603 1239-2",
      "ExternalID": "0760623123929-1-9",
      "AlbumTitle": "Alexandre Glazounov : Intégrale des quatuors à cordes",
      "Rank": 9,
      "NumVolume": 1,
      "PublicationDate": "2011-01-01",
      "LibMusicalKind": "Musique de chambre",
      "Instru": false,
      "SupportType": "Fichier",
      "CDBarCode": "0760623123929",
      "Compositor": {
        "Highlight": true,
        "FullName": "Alexandre Glazounov",
        "Profession": "Compositeur/Compositrice"
      },
      "Interpreter": [
        {
          "FullName": "Quatuor A Cordes D'Utrecht",
          "Profession": "Interprète",
          "InterventionNote": "Quatuor A Cordes D'Utrecht"
        },
        {
          "FullName": "Eeva Koskinen",
          "Profession": "Interprète",
          "InterventionNote": "Eeva Koskinen : Violon",
          "mop": "Violon"
        },
        {
          "FullName": "Katherine Routley",
          "Profession": "Interprète",
          "InterventionNote": "Katherine Routley : Violon",
          "mop": "Violon"
        },
        {
          "FullName": "Joel Waterman",
          "Profession": "Interprète",
          "InterventionNote": "Joel Waterman : Alto (instrument)",
          "mop": "Alto (instrument)"
        },
        {
          "FullName": "Sebastian Koloski",
          "Profession": "Interprète",
          "InterventionNote": "Sebastian Koloski : Violoncelle",
          "mop": "Violoncelle"
        }
      ],
      "ScheduledDateTime": "2017-02-13T02:34:02+01:00",
      "composer": "http://data.doremus.org/artist/064a15a4-b08d-3300-9b18-91ca4e79671c"
    },
    {
      "id": "50",
      "StepID": "50",
      "FatherStepID": "1",
      "AbsoluteScheduledDate": "2017-02-13",
      "ScheduledTime": "02:42:22:00",
      "ScheduledDuration": "00:03:56:00",
      "NumPhase": 49,
      "Inclusion": 0,
      "NumEventCond": 50,
      "TypEvent": "Primary Event",
      "StartMode": "Follow",
      "PressTitle": "Danse hongroise en sol min WoO 1 n°1 - arrangement pour violon et piano",
      "BroadcastNature": "En différé",
      "TechnicalComment": "",
      "Intro1Duration": [
        "00:00:00:00",
        "00:00:00:00"
      ],
      "Intro1DurationMS": 0,
      "SoundId": "Titre de CD",
      "LongTitle": "Danse hongroise en sol min WoO 1 n°1 - arrangement pour violon et piano",
      "Label": "DGG",
      "ReferenceLabel": "4795023",
      "ExternalID": "0028947950233-1-9",
      "AlbumTitle": "Anne-Sophie Mutter : The Club Album - Live from Yellow Lounge",
      "Rank": 9,
      "NumVolume": 1,
      "PublicationDate": "2015-01-01",
      "LibMusicalKind": "Musique de chambre",
      "Instru": false,
      "SupportType": "Fichier",
      "CDBarCode": "0028947950233",
      "Compositor": {
        "Highlight": true,
        "FullName": "Johannes Brahms",
        "Profession": "Compositeur/Compositrice"
      },
      "Interpreter": [
        {
          "FullName": "Anne Sophie Mutter",
          "Profession": "Interprète",
          "InterventionNote": "Anne Sophie Mutter : Violon",
          "mop": "Violon"
        },
        {
          "FullName": "Orkis Lambert",
          "Profession": "Interprète",
          "InterventionNote": "Orkis Lambert : Piano",
          "mop": "Piano"
        }
      ],
      "ScheduledDateTime": "2017-02-13T02:42:22+01:00",
      "composer": "http://data.doremus.org/artist/f9a2ac39-a62d-3be2-8abb-e564de0ec96d",
      "best": "http://data.doremus.org/expression/6b27628b-129e-364e-a3ce-9e2a8546f66a",
      "best_matching_score": "0.99"
    },
    {
      "id": "51",
      "StepID": "51",
      "FatherStepID": "1",
      "AbsoluteScheduledDate": "2017-02-13",
      "ScheduledTime": "02:46:18:00",
      "ScheduledDuration": "00:04:00:00",
      "NumPhase": 50,
      "Inclusion": 0,
      "NumEventCond": 51,
      "TypEvent": "Primary Event",
      "StartMode": "Follow",
      "PressTitle": "Andante e rondo ungarese op 35 J 158 : Andante - pour basson et orchestre",
      "BroadcastNature": "En différé",
      "TechnicalComment": "",
      "Intro1Duration": [
        "00:00:00:00",
        "00:00:00:00"
      ],
      "Intro1DurationMS": 0,
      "SoundId": "Titre de CD",
      "LongTitle": "Andante e rondo ungarese op 35 J 158 : Andante - pour basson et orchestre",
      "Label": "COVIELLO",
      "ReferenceLabel": "COV91517",
      "ExternalID": "4039956915171-1-4",
      "AlbumTitle": "Bassoon Fagott Basson",
      "Rank": 4,
      "NumVolume": 1,
      "PublicationDate": "2015-01-01",
      "LibMusicalKind": "Musique symphonique",
      "Instru": false,
      "SupportType": "Fichier",
      "CDBarCode": "4039956915171",
      "Compositor": {
        "Highlight": true,
        "FullName": "Carl Maria Von Weber",
        "Profession": "Compositeur/Compositrice"
      },
      "Interpreter": {
        "FullName": "Hanno Donneweg",
        "Profession": "Interprète",
        "InterventionNote": "Hanno Donneweg : Basson",
        "mop": "Basson"
      },
      "Orchestra": {
        "EntityName": "Orchestre Symphonique De La Radio De Stuttgart",
        "EntityType": "Orchestre"
      },
      "OrchestraLeader": {
        "FullName": "Gregor Buhl",
        "Profession": "Chef d'orchestre"
      },
      "ScheduledDateTime": "2017-02-13T02:46:18+01:00",
      "composer": "http://data.doremus.org/artist/8000025a-e885-3177-99b3-300707faaad7",
      "best": "http://data.doremus.org/expression/78c53d56-0179-33b3-8ce7-4ef3265025ea",
      "best_matching_score": "1.00"
    },
    {
      "id": "52",
      "StepID": "52",
      "FatherStepID": "1",
      "AbsoluteScheduledDate": "2017-02-13",
      "ScheduledTime": "02:50:18:00",
      "ScheduledDuration": "00:04:02:00",
      "NumPhase": 51,
      "Inclusion": 0,
      "NumEventCond": 52,
      "TypEvent": "Primary Event",
      "StartMode": "Follow",
      "PressTitle": "Concerto en Ré Maj HOB XVIII : 11 pour piano et orchestre : Rondo all ungarese : Allegro assai",
      "BroadcastNature": "En différé",
      "TechnicalComment": "",
      "Intro1Duration": [
        "00:00:00:00",
        "00:00:00:00"
      ],
      "Intro1DurationMS": 0,
      "SoundId": "Titre de CD",
      "LongTitle": "Concerto en Ré Maj HOB XVIII : 11 pour piano et orchestre : Rondo all ungarese : Allegro assai",
      "Label": "DEUTSCHE GRAMOPHON",
      "ReferenceLabel": "439864-2",
      "ExternalID": "0028943986427-1-7",
      "AlbumTitle": "Chostakovitch / Concertos pour piano / Argerich",
      "Rank": 7,
      "NumVolume": 1,
      "PublicationDate": "1994-01-01",
      "LibMusicalKind": "Musique symphonique",
      "Instru": false,
      "SupportType": "Fichier",
      "CDBarCode": "0028943986427",
      "Compositor": {
        "Highlight": true,
        "FullName": "Joseph Haydn",
        "Profession": "Compositeur/Compositrice"
      },
      "Interpreter": {
        "FullName": "Martha Argerich",
        "Profession": "Interprète",
        "InterventionNote": "Martha Argerich : Piano",
        "mop": "Piano"
      },
      "Orchestra": {
        "EntityName": "Orchestre De Chambre De Heilbronn Wurtemberg",
        "EntityType": "Orchestre"
      },
      "OrchestraLeader": {
        "FullName": "Jorg Faerber",
        "Profession": "Chef d'orchestre"
      },
      "ScheduledDateTime": "2017-02-13T02:50:18+01:00",
      "composer": "http://data.doremus.org/artist/12fa21ff-cfa4-31d6-87d9-a22315193b04",
      "best": "http://data.doremus.org/expression/600b36c8-2fdf-3ab8-90e8-dc543ded569c",
      "best_matching_score": "0.74"
    },
    {
      "id": "53",
      "StepID": "53",
      "FatherStepID": "1",
      "AbsoluteScheduledDate": "2017-02-13",
      "ScheduledTime": "02:54:20:00",
      "ScheduledDuration": "00:02:35:00",
      "NumPhase": 52,
      "Inclusion": 0,
      "NumEventCond": 53,
      "TypEvent": "Primary Event",
      "StartMode": "Follow",
      "PressTitle": "7 portraits historiques hongrois S 205 (intégrale) : Deák Ferenc",
      "BroadcastNature": "En différé",
      "TechnicalComment": "",
      "Intro1Duration": [
        "00:00:00:00",
        "00:00:00:00"
      ],
      "Intro1DurationMS": 0,
      "SoundId": "Titre de CD",
      "LongTitle": "7 portraits historiques hongrois S 205 (intégrale) : Deák Ferenc",
      "Label": "DECCA",
      "ReferenceLabel": "476 4089",
      "ExternalID": "RF00000018331-1-8",
      "AlbumTitle": "Franz Liszt : Glanes de Woronince et autres oeuvres",
      "Rank": 8,
      "NumVolume": 1,
      "PublicationDate": "1973-01-01",
      "LibMusicalKind": "Musique de chambre",
      "Instru": false,
      "SupportType": "Fichier",
      "CDBarCode": "RF00000018331",
      "Compositor": {
        "Highlight": true,
        "FullName": "Franz Liszt",
        "Profession": "Compositeur/Compositrice"
      },
      "Interpreter": {
        "FullName": "France Clidat",
        "Profession": "Interprète",
        "InterventionNote": "France Clidat : Piano",
        "mop": "Piano"
      },
      "ScheduledDateTime": "2017-02-13T02:54:20+01:00",
      "composer": "http://data.doremus.org/artist/aabcd2ee-ac9b-30f2-8096-e9de8b3c7a81"
    },
    {
      "id": "54",
      "StepID": "54",
      "FatherStepID": "1",
      "AbsoluteScheduledDate": "2017-02-13",
      "ScheduledTime": "02:56:55:00",
      "ScheduledDuration": "00:03:23:00",
      "NumPhase": 53,
      "Inclusion": 0,
      "NumEventCond": 54,
      "TypEvent": "Primary Event",
      "StartMode": "Follow",
      "PressTitle": "Melodie hongroise en si min D 817",
      "BroadcastNature": "En différé",
      "TechnicalComment": "",
      "Intro1Duration": [
        "00:00:00:00",
        "00:00:00:00"
      ],
      "Intro1DurationMS": 0,
      "SoundId": "Titre de CD",
      "LongTitle": "Melodie hongroise en si min D 817",
      "Label": "PHILIPS",
      "ReferenceLabel": "412703-2",
      "ExternalID": "0028941270320-1-1",
      "AlbumTitle": "Piano romantique",
      "Rank": 1,
      "NumVolume": 1,
      "PublicationDate": "1983-01-01",
      "LibMusicalKind": "Musique de chambre",
      "Instru": false,
      "SupportType": "Fichier",
      "CDBarCode": "0028941270320",
      "Compositor": {
        "Highlight": true,
        "FullName": "Franz Schubert",
        "Profession": "Compositeur/Compositrice"
      },
      "Interpreter": {
        "FullName": "Brigitte Engerer",
        "Profession": "Interprète",
        "InterventionNote": "Brigitte Engerer : Piano",
        "mop": "Piano"
      },
      "ScheduledDateTime": "2017-02-13T02:56:55+01:00",
      "composer": "http://data.doremus.org/artist/03954109-0253-35d6-a70e-89ab27dea09c",
      "best": "http://data.doremus.org/expression/3b2738ce-0c6f-3012-8dda-4644ecea96a3",
      "best_matching_score": "0.99"
    }
  ],
  "total": 45,
  "matched": 18
}